{"type": "BinaryQuadraticModel", "version": {"bqm_schema": "3.0.0"}, "use_bytes": false, "index_type": "int32", "bias_type": "float64", "num_variables": 453, "num_interactions": 3135, "variable_labels": ["Cello_10_blue", "Cello_10_green", "Cello_10_red", "Cello_11_blue", "Cello_11_green", "Cello_11_red", "Cello_12_blue", "Cello_12_green", "Cello_12_red", "Cello_13_blue", "Cello_13_green", "Cello_13_red", "Cello_14_blue", "Cello_14_green", "Cello_14_red", "Cello_15_blue", "Cello_15_green", "Cello_15_red", "Cello_16_blue", "Cello_16_green", "Cello_16_red", "Cello_17_blue", "Cello_17_green", "Cello_17_red", "Cello_18_blue", "Cello_18_green", "Cello_18_red", "Cello_19_blue", "Cello_19_green", "Cello_19_red", "Cello_1_blue", "Cello_1_green", "Cello_1_red", "Cello_20_blue", "Cello_20_green", "Cello_20_red", "Cello_21_blue", "Cello_21_green", "Cello_21_red", "Cello_22_blue", "Cello_22_green", "Cello_22_red", "Cello_23_blue", "Cello_23_green", "Cello_23_red", "Cello_24_blue", "Cello_24_green", "Cello_24_red", "Cello_25_blue", "Cello_25_green", "Cello_25_red", "Cello_26_blue", "Cello_26_green", "Cello_26_red", "Cello_27_blue", "Cello_27_green", "Cello_27_red", "Cello_28_blue", "Cello_28_green", "Cello_28_red", "Cello_29_blue", "Cello_29_green", "Cello_29_red", "Cello_2_blue", "Cello_2_green", "Cello_2_red", "Cello_30_blue", "Cello_30_green", "Cello_30_red", "Cello_31_blue", "Cello_31_green", "Cello_31_red", "Cello_32_blue", "Cello_32_green", "Cello_32_red", "Cello_33_blue", "Cello_33_green", "Cello_33_red", "Cello_34_blue", "Cello_34_green", "Cello_34_red", "Cello_35_blue", "Cello_35_green", "Cello_35_red", "Cello_36_blue", "Cello_36_green", "Cello_36_red", "Cello_37_blue", "Cello_37_green", "Cello_37_red", "Cello_38_blue", "Cello_38_green", "Cello_38_red", "Cello_39_blue", "Cello_39_green", "Cello_39_red", "Cello_3_blue", "Cello_3_green", "Cello_3_red", "Cello_4_blue", "Cello_4_green", "Cello_4_red", "Cello_5_blue", "Cello_5_green", "Cello_5_red", "Cello_6_blue", "Cello_6_green", "Cello_6_red", "Cello_7_blue", "Cello_7_green", "Cello_7_red", "Cello_8_blue", "Cello_8_green", "Cello_8_red", "Cello_9_blue", "Cello_9_green", "Cello_9_red", "Viola_10_blue", "Viola_10_green", "Viola_10_red", "Viola_11_blue", "Viola_11_green", "Viola_11_red", "Viola_12_blue", "Viola_12_green", "Viola_12_red", "Viola_13_blue", "Viola_13_green", "Viola_13_red", "Viola_14_blue", "Viola_14_green", "Viola_14_red", "Viola_15_blue", "Viola_15_green", "Viola_15_red", "Viola_16_blue", "Viola_16_green", "Viola_16_red", "Viola_17_blue", "Viola_17_green", "Viola_17_red", "Viola_18_blue", "Viola_18_green", "Viola_18_red", "Viola_19_blue", "Viola_19_green", "Viola_19_red", "Viola_1_blue", "Viola_1_green", "Viola_1_red", "Viola_20_blue", "Viola_20_green", "Viola_20_red", "Viola_21_blue", "Viola_21_green", "Viola_21_red", "Viola_22_blue", "Viola_22_green", "Viola_22_red", "Viola_23_blue", "Viola_23_green", "Viola_23_red", "Viola_24_blue", "Viola_24_green", "Viola_24_red", "Viola_25_blue", "Viola_25_green", "Viola_25_red", "Viola_26_blue", "Viola_26_green", "Viola_26_red", "Viola_27_blue", "Viola_27_green", "Viola_27_red", "Viola_28_blue", "Viola_28_green", "Viola_28_red", "Viola_29_blue", "Viola_29_green", "Viola_29_red", "Viola_2_blue", "Viola_2_green", "Viola_2_red", "Viola_30_blue", "Viola_30_green", "Viola_30_red", "Viola_31_blue", "Viola_31_green", "Viola_31_red", "Viola_3_blue", "Viola_3_green", "Viola_3_red", "Viola_4_blue", "Viola_4_green", "Viola_4_red", "Viola_5_blue", "Viola_5_green", "Viola_5_red", "Viola_6_blue", "Viola_6_green", "Viola_6_red", "Viola_7_blue", "Viola_7_green", "Viola_7_red", "Viola_8_blue", "Viola_8_green", "Viola_8_red", "Viola_9_blue", "Viola_9_green", "Viola_9_red", "Violin II_10_blue", "Violin II_10_green", "Violin II_10_red", "Violin II_11_blue", "Violin II_11_green", "Violin II_11_red", "Violin II_12_blue", "Violin II_12_green", "Violin II_12_red", "Violin II_13_blue", "Violin II_13_green", "Violin II_13_red", "Violin II_14_blue", "Violin II_14_green", "Violin II_14_red", "Violin II_15_blue", "Violin II_15_green", "Violin II_15_red", "Violin II_16_blue", "Violin II_16_green", "Violin II_16_red", "Violin II_17_blue", "Violin II_17_green", "Violin II_17_red", "Violin II_18_blue", "Violin II_18_green", "Violin II_18_red", "Violin II_19_blue", "Violin II_19_green", "Violin II_19_red", "Violin II_1_blue", "Violin II_1_green", "Violin II_1_red", "Violin II_20_blue", "Violin II_20_green", "Violin II_20_red", "Violin II_21_blue", "Violin II_21_green", "Violin II_21_red", "Violin II_22_blue", "Violin II_22_green", "Violin II_22_red", "Violin II_23_blue", "Violin II_23_green", "Violin II_23_red", "Violin II_24_blue", "Violin II_24_green", "Violin II_24_red", "Violin II_25_blue", "Violin II_25_green", "Violin II_25_red", "Violin II_26_blue", "Violin II_26_green", "Violin II_26_red", "Violin II_27_blue", "Violin II_27_green", "Violin II_27_red", "Violin II_28_blue", "Violin II_28_green", "Violin II_28_red", "Violin II_29_blue", "Violin II_29_green", "Violin II_29_red", "Violin II_2_blue", "Violin II_2_green", "Violin II_2_red", "Violin II_30_blue", "Violin II_30_green", "Violin II_30_red", "Violin II_31_blue", "Violin II_31_green", "Violin II_31_red", "Violin II_32_blue", "Violin II_32_green", "Violin II_32_red", "Violin II_33_blue", "Violin II_33_green", "Violin II_33_red", "Violin II_34_blue", "Violin II_34_green", "Violin II_34_red", "Violin II_35_blue", "Violin II_35_green", "Violin II_35_red", "Violin II_36_blue", "Violin II_36_green", "Violin II_36_red", "Violin II_37_blue", "Violin II_37_green", "Violin II_37_red", "Violin II_38_blue", "Violin II_38_green", "Violin II_38_red", "Violin II_39_blue", "Violin II_39_green", "Violin II_39_red", "Violin II_3_blue", "Violin II_3_green", "Violin II_3_red", "Violin II_40_blue", "Violin II_40_green", "Violin II_40_red", "Violin II_41_blue", "Violin II_41_green", "Violin II_41_red", "Violin II_42_blue", "Violin II_42_green", "Violin II_42_red", "Violin II_4_blue", "Violin II_4_green", "Violin II_4_red", "Violin II_5_blue", "Violin II_5_green", "Violin II_5_red", "Violin II_6_blue", "Violin II_6_green", "Violin II_6_red", "Violin II_7_blue", "Violin II_7_green", "Violin II_7_red", "Violin II_8_blue", "Violin II_8_green", "Violin II_8_red", "Violin II_9_blue", "Violin II_9_green", "Violin II_9_red", "Violin I_10_blue", "Violin I_10_green", "Violin I_10_red", "Violin I_11_blue", "Violin I_11_green", "Violin I_11_red", "Violin I_12_blue", "Violin I_12_green", "Violin I_12_red", "Violin I_13_blue", "Violin I_13_green", "Violin I_13_red", "Violin I_14_blue", "Violin I_14_green", "Violin I_14_red", "Violin I_15_blue", "Violin I_15_green", "Violin I_15_red", "Violin I_16_blue", "Violin I_16_green", "Violin I_16_red", "Violin I_17_blue", "Violin I_17_green", "Violin I_17_red", "Violin I_18_blue", "Violin I_18_green", "Violin I_18_red", "Violin I_19_blue", "Violin I_19_green", "Violin I_19_red", "Violin I_1_blue", "Violin I_1_green", "Violin I_1_red", "Violin I_20_blue", "Violin I_20_green", "Violin I_20_red", "Violin I_21_blue", "Violin I_21_green", "Violin I_21_red", "Violin I_22_blue", "Violin I_22_green", "Violin I_22_red", "Violin I_23_blue", "Violin I_23_green", "Violin I_23_red", "Violin I_24_blue", "Violin I_24_green", "Violin I_24_red", "Violin I_25_blue", "Violin I_25_green", "Violin I_25_red", "Violin I_26_blue", "Violin I_26_green", "Violin I_26_red", "Violin I_27_blue", "Violin I_27_green", "Violin I_27_red", "Violin I_28_blue", "Violin I_28_green", "Violin I_28_red", "Violin I_29_blue", "Violin I_29_green", "Violin I_29_red", "Violin I_2_blue", "Violin I_2_green", "Violin I_2_red", "Violin I_30_blue", "Violin I_30_green", "Violin I_30_red", "Violin I_31_blue", "Violin I_31_green", "Violin I_31_red", "Violin I_32_blue", "Violin I_32_green", "Violin I_32_red", "Violin I_33_blue", "Violin I_33_green", "Violin I_33_red", "Violin I_34_blue", "Violin I_34_green", "Violin I_34_red", "Violin I_35_blue", "Violin I_35_green", "Violin I_35_red", "Violin I_36_blue", "Violin I_36_green", "Violin I_36_red", "Violin I_37_blue", "Violin I_37_green", "Violin I_37_red", "Violin I_38_blue", "Violin I_38_green", "Violin I_38_red", "Violin I_39_blue", "Violin I_39_green", "Violin I_39_red", "Violin I_3_blue", "Violin I_3_green", "Violin I_3_red", "Violin I_4_blue", "Violin I_4_green", "Violin I_4_red", "Violin I_5_blue", "Violin I_5_green", "Violin I_5_red", "Violin I_6_blue", "Violin I_6_green", "Violin I_6_red", "Violin I_7_blue", "Violin I_7_green", "Violin I_7_red", "Violin I_8_blue", "Violin I_8_green", "Violin I_8_red", "Violin I_9_blue", "Violin I_9_green", "Violin I_9_red"], "variable_type": "BINARY", "offset": 0.0, "info": {}, "linear_biases": [-2.0, -2.0, -2.0, 0.0, 0.0, 0.0, 0.0, 0.0, 0.0, -2.5, -2.5, -2.5, 0.0, 0.0, 0.0, -0.9940302114769565, -0.9940302114769565, -0.9940302114769565, -2.822826731935328, -2.822826731935328, -2.822826731935328, 0.0, 0.0, 0.0, 0.0, 0.0, 0.0, 0.0, 0.0, 0.0, -2.5418848434970744, -2.5418848434970744, -2.5418848434970744, -3.5219280948873624, -3.5219280948873624, -3.5219280948873624, -1.4438561897747246, -1.4438561897747246, -1.4438561897747246, 0.0, 0.0, 0.0, -2.257469499888181, -2.257469499888181, -2.257469499888181, 0.0, 0.0, 0.0, 0.0, 0.0, 0.0, -2.561278124459133, -2.561278124459133, -2.561278124459133, 0.0, 0.0, 0.0, -2.836591668108979, -2.836591668108979, -2.836591668108979, 0.0, 0.0, 0.0, 0.0, 0.0, 0.0, -1.6225562489182657, -1.6225562489182657, -1.6225562489182657, 0.0, 0.0, 0.0, 0.0, 0.0, 0.0, 0.0, 0.0, 0.0, 0.0, 0.0, 0.0, -1.0, -1.0, -1.0, -2.0, -2.0, -2.0, 0.0, 0.0, 0.0, -1.764636437170162, -1.764636437170162, -1.764636437170162, -2.668418918896098, -2.668418918896098, -2.668418918896098, -2.377443751081734, -2.377443751081734, -2.377443751081734, 0.0, 0.0, 0.0, 0.0, 0.0, 0.0, 0.0, 0.0, 0.0, -1.0, -1.0, -1.0, 0.0, 0.0, 0.0, -2.892878689342031, -2.892878689342031, -2.892878689342031, -2.8190699894100915, -2.8190699894100915, -2.8190699894100915, 0.0, 0.0, 0.0, -1.5, -1.5, -1.5, 0.0, 0.0, 0.0, -2.7506120151057627, -2.7506120151057627, -2.7506120151057627, 0.0, 0.0, 0.0, -1.5, -1.5, -1.5, -2.0, -2.0, -2.0, -3.653011832142705, -3.653011832142705, -3.653011832142705, 0.0, 0.0, 0.0, -2.5, -2.5, -2.5, -1.5, -1.5, -1.5, -2.5, -2.5, -2.5, 0.0, 0.0, 0.0, -3.5612781244591325, -3.5612781244591325, -3.5612781244591325, 0.0, 0.0, 0.0, -3.0, -3.0, -3.0, 0.0, 0.0, 0.0, -1.221694907636328, -1.221694907636328, -1.221694907636328, -2.5683182557028434, -2.5683182557028434, -2.5683182557028434, -2.311278124459133, -2.311278124459133, -2.311278124459133, -1.5, -1.5, -1.5, 0.0, 0.0, 0.0, -1.9182958340544896, -1.9182958340544896, -1.9182958340544896, -2.5, -2.5, -2.5, 0.0, 0.0, 0.0, -3.029423942181382, -3.029423942181382, -3.029423942181382, 0.0, 0.0, 0.0, -3.2674628412842663, -3.2674628412842663, -3.2674628412842663, 0.0, 0.0, 0.0, -1.4366664819166874, -1.4366664819166874, -1.4366664819166874, -3.1468524060359133, -3.1468524060359133, -3.1468524060359133, 0.0, 0.0, 0.0, -1.5, -1.5, -1.5, 0.0, 0.0, 0.0, -1.5, -1.5, -1.5, 0.0, 0.0, 0.0, -1.0, -1.0, -1.0, 0.0, 0.0, 0.0, -1.0, -1.0, -1.0, 0.0, 0.0, 0.0, -2.976216224524763, -2.976216224524763, -2.976216224524763, -2.710777084415067, -2.710777084415067, -2.710777084415067, 0.0, 0.0, 0.0, -1.5, -1.5, -1.5, 0.0, 0.0, 0.0, -3.219973094021975, -3.219973094021975, -3.219973094021975, 0.0, 0.0, 0.0, -2.976216224524763, -2.976216224524763, -2.976216224524763, 0.0, 0.0, 0.0, -3.0735173629140013, -3.0735173629140013, -3.0735173629140013, 0.0, 0.0, 0.0, 0.0, 0.0, 0.0, 0.0, 0.0, 0.0, 0.0, 0.0, 0.0, -2.9016515890361765, -2.9016515890361765, -2.9016515890361765, 0.0, 0.0, 0.0, -3.0168256410920224, -3.0168256410920224, -3.0168256410920224, 0.0, 0.0, 0.0, -3.4509611139957355, -3.4509611139957355, -3.4509611139957355, -3.503258334775645, -3.503258334775645, -3.503258334775645, 0.0, 0.0, 0.0, 0.0, 0.0, 0.0, -3.576911051568265, -3.576911051568265, -3.576911051568265, -2.9212115599075865, -2.9212115599075865, -2.9212115599075865, 0.0, 0.0, 0.0, -1.576900914616579, -1.576900914616579, -1.576900914616579, -1.0, -1.0, -1.0, 0.0, 0.0, 0.0, -0.9182958340544896, -0.9182958340544896, -0.9182958340544896, 0.0, 0.0, 0.0, -2.7527152789797045, -2.7527152789797045, -2.7527152789797045, 0.0, 0.0, 0.0, 0.0, 0.0, 0.0, -2.4340437717594363, -2.4340437717594363, -2.4340437717594363, 0.0, 0.0, 0.0, -2.4340437717594363, -2.4340437717594363, -2.4340437717594363, 0.0, 0.0, 0.0, -1.0, -1.0, -1.0, 0.0, 0.0, 0.0, -1.0, -1.0, -1.0, 0.0, 0.0, 0.0, -0.7219280948873623, -0.7219280948873623, -0.7219280948873623, -2.7024549619059113, -2.7024549619059113, -2.7024549619059113, 0.0, 0.0, 0.0, -2.364011629520427, -2.364011629520427, -2.364011629520427, 0.0, 0.0, 0.0, -0.9709505944546686, -0.9709505944546686, -0.9709505944546686, 0.0, 0.0, 0.0, -3.1452473277903277, -3.1452473277903277, -3.1452473277903277, -1.584962500721156, -1.584962500721156, -1.584962500721156, -1.0, -1.0, -1.0, 0.0, 0.0, 0.0, -2.7024549619059113, -2.7024549619059113, -2.7024549619059113, 0.0, 0.0, 0.0, 0.0, 0.0, 0.0, -2.935440200948998, -2.935440200948998, -2.935440200948998, 0.0, 0.0, 0.0, -0.9182958340544896, -0.9182958340544896, -0.9182958340544896, 0.0, 0.0, 0.0, -3.6620955904995, -3.6620955904995, -3.6620955904995, 0.0, 0.0, 0.0, -1.9182958340544893, -1.9182958340544893, -1.9182958340544893, 0.0, 0.0, 0.0, -3.9377202638687443, -3.9377202638687443, -3.9377202638687443, -2.7736843762620236, -2.7736843762620236, -2.7736843762620236, 0.0, 0.0, 0.0, -3.3532404802626123, -3.3532404802626123, -3.3532404802626123, 0.0, 0.0, 0.0, -1.9182958340544893, -1.9182958340544893, -1.9182958340544893, 0.0, 0.0, 0.0, -3.8689641616683996, -3.8689641616683996, -3.8689641616683996], "quadratic_biases": [2.0, 2.0, 8.0, -2.0, -2.0, 8.732537158715733, -1.2674628412842663, -1.2674628412842663, 8.0, -2.0, -2.0, 8.646759519737387, -1.3532404802626123, -1.3532404802626123, 2.0, -2.0, 8.0, -2.0, -1.2674628412842663, 8.732537158715733, -1.2674628412842663, -2.0, 8.0, -2.0, -1.3532404802626123, 8.646759519737387, -1.3532404802626123, -2.0, -2.0, 8.0, -1.2674628412842663, -1.2674628412842663, 8.732537158715733, -2.0, -2.0, 8.0, -1.3532404802626123, -1.3532404802626123, 8.646759519737387, 2.0, 2.0, 6.732537158715734, -3.2674628412842663, -3.2674628412842663, 6.646759519737388, -3.3532404802626123, -3.3532404802626123, 2.0, -3.2674628412842663, 6.732537158715734, -3.2674628412842663, -3.3532404802626123, 6.646759519737388, -3.3532404802626123, -3.2674628412842663, -3.2674628412842663, 6.732537158715734, -3.3532404802626123, -3.3532404802626123, 6.646759519737388, 2.0, 2.0, 6.732537158715734, -3.2674628412842663, -3.2674628412842663, 6.646759519737388, -3.3532404802626123, -3.3532404802626123, 2.0, -3.2674628412842663, 6.732537158715734, -3.2674628412842663, -3.3532404802626123, 6.646759519737388, -3.3532404802626123, -3.2674628412842663, -3.2674628412842663, 6.732537158715734, -3.3532404802626123, -3.3532404802626123, 6.646759519737388, 2.0, 2.0, 9.232537158715733, -0.7674628412842663, -0.7674628412842663, 9.747284721020296, -0.25271527897970447, -0.25271527897970447, 9.146759519737387, -0.8532404802626123, -0.8532404802626123, 2.0, -0.7674628412842663, 9.232537158715733, -0.7674628412842663, -0.25271527897970447, 9.747284721020296, -0.25271527897970447, -0.8532404802626123, 9.146759519737387, -0.8532404802626123, -0.7674628412842663, -0.7674628412842663, 9.232537158715733, -0.25271527897970447, -0.25271527897970447, 9.747284721020296, -0.8532404802626123, -0.8532404802626123, 9.146759519737387, 2.0, 2.0, 10.0, 0.0, 0.0, 7.2472847210202955, -2.7527152789797045, -2.7527152789797045, 6.646759519737388, -3.3532404802626123, -3.3532404802626123, 2.0, 0.0, 10.0, 0.0, -2.7527152789797045, 7.2472847210202955, -2.7527152789797045, -3.3532404802626123, 6.646759519737388, -3.3532404802626123, 0.0, 0.0, 10.0, -2.7527152789797045, -2.7527152789797045, 7.2472847210202955, -3.3532404802626123, -3.3532404802626123, 6.646759519737388, 2.0, 2.0, 9.557363729560269, -0.44263627043973097, -0.44263627043973097, 7.847177805441043, -2.152822194558957, -2.152822194558957, 7.640789731214344, -2.359210268785656, -2.359210268785656, 9.005969788523043, -0.9940302114769565, -0.9940302114769565, 9.075734377422467, -0.9242656225775329, -0.9242656225775329, 9.005969788523043, -0.9940302114769565, -0.9940302114769565, 7.125066049808557, -2.8749339501914433, -2.8749339501914433, 2.0, -0.44263627043973097, 9.557363729560269, -0.44263627043973097, -2.152822194558957, 7.847177805441043, -2.152822194558957, -2.359210268785656, 7.640789731214344, -2.359210268785656, -0.9940302114769565, 9.005969788523043, -0.9940302114769565, -0.9242656225775329, 9.075734377422467, -0.9242656225775329, -0.9940302114769565, 9.005969788523043, -0.9940302114769565, -2.8749339501914433, 7.125066049808557, -2.8749339501914433, -0.44263627043973097, -0.44263627043973097, 9.557363729560269, -2.152822194558957, -2.152822194558957, 7.847177805441043, -2.359210268785656, -2.359210268785656, 7.640789731214344, -0.9940302114769565, -0.9940302114769565, 9.005969788523043, -0.9242656225775329, -0.9242656225775329, 9.075734377422467, -0.9940302114769565, -0.9940302114769565, 9.005969788523043, -2.8749339501914433, -2.8749339501914433, 7.125066049808557, 2.0, 2.0, 9.996243257474763, -0.0037567425252365005, -0.0037567425252365005, 9.675974325899414, -0.32402567410058536, -0.32402567410058536, 8.953862570266928, -1.0461374297330717, -1.0461374297330717, 2.0, -0.0037567425252365005, 9.996243257474763, -0.0037567425252365005, -0.32402567410058536, 9.675974325899414, -0.32402567410058536, -1.0461374297330717, 8.953862570266928, -1.0461374297330717, -0.0037567425252365005, -0.0037567425252365005, 9.996243257474763, -0.32402567410058536, -0.32402567410058536, 9.675974325899414, -1.0461374297330717, -1.0461374297330717, 8.953862570266928, 2.0, 2.0, 10.0, 0.0, 0.0, 10.0, 0.0, 0.0, 10.0, 0.0, 0.0, 2.0, 0.0, 10.0, 0.0, 0.0, 10.0, 0.0, 0.0, 10.0, 0.0, 0.0, 0.0, 10.0, 0.0, 0.0, 10.0, 0.0, 0.0, 10.0, 2.0, 2.0, 8.5, -1.5, -1.5, 8.5, -1.5, -1.5, 2.0, -1.5, 8.5, -1.5, -1.5, 8.5, -1.5, -1.5, -1.5, 8.5, -1.5, -1.5, 8.5, 2.0, 2.0, 10.0, 0.0, 0.0, 10.0, 0.0, 0.0, 2.0, 0.0, 10.0, 0.0, 0.0, 10.0, 0.0, 0.0, 0.0, 10.0, 0.0, 0.0, 10.0, 2.0, 2.0, 9.958115156502926, -0.04188484349707444, -0.04188484349707444, 9.56566861897231, -0.43433138102768876, -0.43433138102768876, 9.839429881591164, -0.16057011840883684, -0.16057011840883684, 2.0, -0.04188484349707444, 9.958115156502926, -0.04188484349707444, -0.43433138102768876, 9.56566861897231, -0.43433138102768876, -0.16057011840883684, 9.839429881591164, -0.16057011840883684, -0.04188484349707444, -0.04188484349707444, 9.958115156502926, -0.43433138102768876, -0.43433138102768876, 9.56566861897231, -0.16057011840883684, -0.16057011840883684, 9.839429881591164, 2.0, 2.0, 9.228683920218401, -0.7713160797815997, -0.7713160797815997, 7.978071905112637, -2.0219280948873624, -2.0219280948873624, 6.478071905112637, -3.5219280948873624, -3.5219280948873624, 7.478071905112637, -2.5219280948873624, -2.5219280948873624, 6.478071905112637, -3.5219280948873624, -3.5219280948873624, 7.478071905112637, -2.5219280948873624, -2.5219280948873624, 6.478071905112637, -3.5219280948873624, -3.5219280948873624, 7.478071905112637, -2.5219280948873624, -2.5219280948873624, 6.478071905112637, -3.5219280948873624, -3.5219280948873624, 7.478071905112637, -2.5219280948873624, -2.5219280948873624, 6.478071905112637, -3.5219280948873624, -3.5219280948873624, 7.2, -2.8, -2.8, 2.0, -0.7713160797815997, 9.228683920218401, -0.7713160797815997, -2.0219280948873624, 7.978071905112637, -2.0219280948873624, -3.5219280948873624, 6.478071905112637, -3.5219280948873624, -2.5219280948873624, 7.478071905112637, -2.5219280948873624, -3.5219280948873624, 6.478071905112637, -3.5219280948873624, -2.5219280948873624, 7.478071905112637, -2.5219280948873624, -3.5219280948873624, 6.478071905112637, -3.5219280948873624, -2.5219280948873624, 7.478071905112637, -2.5219280948873624, -3.5219280948873624, 6.478071905112637, -3.5219280948873624, -2.5219280948873624, 7.478071905112637, -2.5219280948873624, -3.5219280948873624, 6.478071905112637, -3.5219280948873624, -2.8, 7.2, -2.8, -0.7713160797815997, -0.7713160797815997, 9.228683920218401, -2.0219280948873624, -2.0219280948873624, 7.978071905112637, -3.5219280948873624, -3.5219280948873624, 6.478071905112637, -2.5219280948873624, -2.5219280948873624, 7.478071905112637, -3.5219280948873624, -3.5219280948873624, 6.478071905112637, -2.5219280948873624, -2.5219280948873624, 7.478071905112637, -3.5219280948873624, -3.5219280948873624, 6.478071905112637, -2.5219280948873624, -2.5219280948873624, 7.478071905112637, -3.5219280948873624, -3.5219280948873624, 6.478071905112637, -2.5219280948873624, -2.5219280948873624, 7.478071905112637, -3.5219280948873624, -3.5219280948873624, 6.478071905112637, -2.8, -2.8, 7.2, 2.0, 2.0, 8.556143810225276, -1.4438561897747246, -1.4438561897747246, 9.943856189774724, -0.05614381022527537, -0.05614381022527537, 8.733079105359657, -1.2669208946403425, -1.2669208946403425, 9.278071905112638, -0.7219280948873623, -0.7219280948873623, 8.556143810225276, -1.4438561897747246, -1.4438561897747246, 2.0, -1.4438561897747246, 8.556143810225276, -1.4438561897747246, -0.05614381022527537, 9.943856189774724, -0.05614381022527537, -1.2669208946403425, 8.733079105359657, -1.2669208946403425, -0.7219280948873623, 9.278071905112638, -0.7219280948873623, -1.4438561897747246, 8.556143810225276, -1.4438561897747246, -1.4438561897747246, -1.4438561897747246, 8.556143810225276, -0.05614381022527537, -0.05614381022527537, 9.943856189774724, -1.2669208946403425, -1.2669208946403425, 8.733079105359657, -0.7219280948873623, -0.7219280948873623, 9.278071905112638, -1.4438561897747246, -1.4438561897747246, 8.556143810225276, 2.0, 2.0, 8.0, -2.0, -2.0, 7.289222915584933, -2.710777084415067, -2.710777084415067, 2.0, -2.0, 8.0, -2.0, -2.710777084415067, 7.289222915584933, -2.710777084415067, -2.0, -2.0, 8.0, -2.710777084415067, -2.710777084415067, 7.289222915584933, 2.0, 2.0, 8.604457667745475, -1.3955423322545242, -1.3955423322545242, 9.242530500111819, -0.757469499888181, -0.757469499888181, 7.742530500111819, -2.257469499888181, -2.257469499888181, 9.037496405866206, -0.962503594133794, -0.962503594133794, 8.713481094566488, -1.2865189054335124, -1.2865189054335124, 7.742530500111819, -2.257469499888181, -2.257469499888181, 9.112222172097853, -0.8877778279021467, -0.8877778279021467, 2.0, -1.3955423322545242, 8.604457667745475, -1.3955423322545242, -0.757469499888181, 9.242530500111819, -0.757469499888181, -2.257469499888181, 7.742530500111819, -2.257469499888181, -0.962503594133794, 9.037496405866206, -0.962503594133794, -1.2865189054335124, 8.713481094566488, -1.2865189054335124, -2.257469499888181, 7.742530500111819, -2.257469499888181, -0.8877778279021467, 9.112222172097853, -0.8877778279021467, -1.3955423322545242, -1.3955423322545242, 8.604457667745475, -0.757469499888181, -0.757469499888181, 9.242530500111819, -2.257469499888181, -2.257469499888181, 7.742530500111819, -0.962503594133794, -0.962503594133794, 9.037496405866206, -1.2865189054335124, -1.2865189054335124, 8.713481094566488, -2.257469499888181, -2.257469499888181, 7.742530500111819, -0.8877778279021467, -0.8877778279021467, 9.112222172097853, 2.0, 2.0, 6.346988167857295, -3.653011832142705, -3.653011832142705, 6.7800269059780245, -3.219973094021975, -3.219973094021975, 6.854752672209672, -3.1452473277903277, -3.1452473277903277, 2.0, -3.653011832142705, 6.346988167857295, -3.653011832142705, -3.219973094021975, 6.7800269059780245, -3.219973094021975, -3.1452473277903277, 6.854752672209672, -3.1452473277903277, -3.653011832142705, -3.653011832142705, 6.346988167857295, -3.219973094021975, -3.219973094021975, 6.7800269059780245, -3.1452473277903277, -3.1452473277903277, 6.854752672209672, 2.0, 2.0, 6.346988167857295, -3.653011832142705, -3.653011832142705, 6.7800269059780245, -3.219973094021975, -3.219973094021975, 6.854752672209672, -3.1452473277903277, -3.1452473277903277, 8.415037499278844, -1.584962500721156, -1.584962500721156, 9.0, -1.0, -1.0, 2.0, -3.653011832142705, 6.346988167857295, -3.653011832142705, -3.219973094021975, 6.7800269059780245, -3.219973094021975, -3.1452473277903277, 6.854752672209672, -3.1452473277903277, -1.584962500721156, 8.415037499278844, -1.584962500721156, -1.0, 9.0, -1.0, -3.653011832142705, -3.653011832142705, 6.346988167857295, -3.219973094021975, -3.219973094021975, 6.7800269059780245, -3.1452473277903277, -3.1452473277903277, 6.854752672209672, -1.584962500721156, -1.584962500721156, 8.415037499278844, -1.0, -1.0, 9.0, 2.0, 2.0, 8.908266292316428, -1.0917337076835723, -1.0917337076835723, 7.4387218755408675, -2.561278124459133, -2.561278124459133, 9.58506189993437, -0.41493810006563026, -0.41493810006563026, 7.4387218755408675, -2.561278124459133, -2.561278124459133, 9.858823162553222, -0.14117683744677834, -0.14117683744677834, 2.0, -1.0917337076835723, 8.908266292316428, -1.0917337076835723, -2.561278124459133, 7.4387218755408675, -2.561278124459133, -0.41493810006563026, 9.58506189993437, -0.41493810006563026, -2.561278124459133, 7.4387218755408675, -2.561278124459133, -0.14117683744677834, 9.858823162553222, -0.14117683744677834, -1.0917337076835723, -1.0917337076835723, 8.908266292316428, -2.561278124459133, -2.561278124459133, 7.4387218755408675, -0.41493810006563026, -0.41493810006563026, 9.58506189993437, -2.561278124459133, -2.561278124459133, 7.4387218755408675, -0.14117683744677834, -0.14117683744677834, 9.858823162553222, 2.0, 2.0, 10.0, 0.0, 0.0, 7.023783775475237, -2.976216224524763, -2.976216224524763, 7.297545038094089, -2.7024549619059113, -2.7024549619059113, 2.0, 0.0, 10.0, 0.0, -2.976216224524763, 7.023783775475237, -2.976216224524763, -2.7024549619059113, 7.297545038094089, -2.7024549619059113, 0.0, 0.0, 10.0, -2.976216224524763, -2.976216224524763, 7.023783775475237, -2.7024549619059113, -2.7024549619059113, 7.297545038094089, 2.0, 2.0, 8.66340833189102, -1.3365916681089791, -1.3365916681089791, 9.66340833189102, -0.3365916681089791, -0.3365916681089791, 9.860375443584216, -0.13962455641578408, -0.13962455641578408, 7.163408331891021, -2.836591668108979, -2.836591668108979, 9.763074305194978, -0.23692569480502224, -0.23692569480502224, 9.90115146715998, -0.09884853284001904, -0.09884853284001904, 2.0, -1.3365916681089791, 8.66340833189102, -1.3365916681089791, -0.3365916681089791, 9.66340833189102, -0.3365916681089791, -0.13962455641578408, 9.860375443584216, -0.13962455641578408, -2.836591668108979, 7.163408331891021, -2.836591668108979, -0.23692569480502224, 9.763074305194978, -0.23692569480502224, -0.09884853284001904, 9.90115146715998, -0.09884853284001904, -1.3365916681089791, -1.3365916681089791, 8.66340833189102, -0.3365916681089791, -0.3365916681089791, 9.66340833189102, -0.13962455641578408, -0.13962455641578408, 9.860375443584216, -2.836591668108979, -2.836591668108979, 7.163408331891021, -0.23692569480502224, -0.23692569480502224, 9.763074305194978, -0.09884853284001904, -0.09884853284001904, 9.90115146715998, 2.0, 2.0, 10.0, 0.0, 0.0, 6.926482637085998, -3.0735173629140013, -3.0735173629140013, 10.0, 0.0, 0.0, 2.0, 0.0, 10.0, 0.0, -3.0735173629140013, 6.926482637085998, -3.0735173629140013, 0.0, 10.0, 0.0, 0.0, 0.0, 10.0, -3.0735173629140013, -3.0735173629140013, 6.926482637085998, 0.0, 0.0, 10.0, 2.0, 2.0, 7.5, -2.5, -2.5, 7.023783775475237, -2.976216224524763, -2.976216224524763, 7.297545038094089, -2.7024549619059113, -2.7024549619059113, 2.0, -2.5, 7.5, -2.5, -2.976216224524763, 7.023783775475237, -2.976216224524763, -2.7024549619059113, 7.297545038094089, -2.7024549619059113, -2.5, -2.5, 7.5, -2.976216224524763, -2.976216224524763, 7.023783775475237, -2.7024549619059113, -2.7024549619059113, 7.297545038094089, 2.0, 2.0, 8.061278124459132, -1.9387218755408668, -1.9387218755408668, 8.549038886004265, -1.4509611139957357, -1.4509611139957357, 2.0, -1.9387218755408668, 8.061278124459132, -1.9387218755408668, -1.4509611139957357, 8.549038886004265, -1.4509611139957357, -1.9387218755408668, -1.9387218755408668, 8.061278124459132, -1.4509611139957357, -1.4509611139957357, 8.549038886004265, 2.0, 2.0, 6.4387218755408675, -3.5612781244591325, -3.5612781244591325, 10.0, 0.0, 0.0, 6.3379044095005, -3.6620955904995, -3.6620955904995, 2.0, -3.5612781244591325, 6.4387218755408675, -3.5612781244591325, 0.0, 10.0, 0.0, -3.6620955904995, 6.3379044095005, -3.6620955904995, -3.5612781244591325, -3.5612781244591325, 6.4387218755408675, 0.0, 0.0, 10.0, -3.6620955904995, -3.6620955904995, 6.3379044095005, 2.0, 2.0, 6.4387218755408675, -3.5612781244591325, -3.5612781244591325, 10.0, 0.0, 0.0, 6.3379044095005, -3.6620955904995, -3.6620955904995, 2.0, -3.5612781244591325, 6.4387218755408675, -3.5612781244591325, 0.0, 10.0, 0.0, -3.6620955904995, 6.3379044095005, -3.6620955904995, -3.5612781244591325, -3.5612781244591325, 6.4387218755408675, 0.0, 0.0, 10.0, -3.6620955904995, -3.6620955904995, 6.3379044095005, 2.0, 2.0, 6.4387218755408675, -3.5612781244591325, -3.5612781244591325, 10.0, 0.0, 0.0, 6.3379044095005, -3.6620955904995, -3.6620955904995, 2.0, -3.5612781244591325, 6.4387218755408675, -3.5612781244591325, 0.0, 10.0, 0.0, -3.6620955904995, 6.3379044095005, -3.6620955904995, -3.5612781244591325, -3.5612781244591325, 6.4387218755408675, 0.0, 0.0, 10.0, -3.6620955904995, -3.6620955904995, 6.3379044095005, 2.0, 2.0, 10.0, 0.0, 0.0, 7.0983484109638235, -2.9016515890361765, -2.9016515890361765, 6.3379044095005, -3.6620955904995, -3.6620955904995, 2.0, 0.0, 10.0, 0.0, -2.9016515890361765, 7.0983484109638235, -2.9016515890361765, -3.6620955904995, 6.3379044095005, -3.6620955904995, 0.0, 0.0, 10.0, -2.9016515890361765, -2.9016515890361765, 7.0983484109638235, -3.6620955904995, -3.6620955904995, 6.3379044095005, 2.0, 2.0, 8.0, -2.0, -2.0, 8.098348410963823, -1.9016515890361765, -1.9016515890361765, 9.0, -1.0, -1.0, 7.3379044095005, -2.6620955904995, -2.6620955904995, 2.0, -2.0, 8.0, -2.0, -1.9016515890361765, 8.098348410963823, -1.9016515890361765, -1.0, 9.0, -1.0, -2.6620955904995, 7.3379044095005, -2.6620955904995, -2.0, -2.0, 8.0, -1.9016515890361765, -1.9016515890361765, 8.098348410963823, -1.0, -1.0, 9.0, -2.6620955904995, -2.6620955904995, 7.3379044095005, 2.0, 2.0, 9.0, -1.0, -1.0, 8.983174358907977, -1.0168256410920224, -1.0168256410920224, 8.3379044095005, -1.6620955904994998, -1.6620955904994998, 2.0, -1.0, 9.0, -1.0, -1.0168256410920224, 8.983174358907977, -1.0168256410920224, -1.6620955904994998, 8.3379044095005, -1.6620955904994998, -1.0, -1.0, 9.0, -1.0168256410920224, -1.0168256410920224, 8.983174358907977, -1.6620955904994998, -1.6620955904994998, 8.3379044095005, 2.0, 2.0, 10.0, 0.0, 0.0, 6.983174358907977, -3.0168256410920224, -3.0168256410920224, 6.3379044095005, -3.6620955904995, -3.6620955904995, 2.0, 0.0, 10.0, 0.0, -3.0168256410920224, 6.983174358907977, -3.0168256410920224, -3.6620955904995, 6.3379044095005, -3.6620955904995, 0.0, 0.0, 10.0, -3.0168256410920224, -3.0168256410920224, 6.983174358907977, -3.6620955904995, -3.6620955904995, 6.3379044095005, 2.0, 2.0, 9.457058470466166, -0.542941529533834, -0.542941529533834, 9.19631818146732, -0.8036818185326815, -0.8036818185326815, 8.313675323174426, -1.6863246768255735, -1.6863246768255735, 8.261378102394517, -1.7386218976054832, -1.7386218976054832, 8.235363562829837, -1.764636437170162, -1.764636437170162, 8.235363562829837, -1.764636437170162, -1.764636437170162, 8.843424877262576, -1.1565751227374246, -1.1565751227374246, 8.102540846670662, -1.897459153329338, -1.897459153329338, 8.235363562829837, -1.764636437170162, -1.764636437170162, 9.846340603115673, -0.1536593968843274, -0.1536593968843274, 8.235363562829837, -1.764636437170162, -1.764636437170162, 7.826916173301417, -2.1730838266985826, -2.1730838266985826, 2.0, -0.542941529533834, 9.457058470466166, -0.542941529533834, -0.8036818185326815, 9.19631818146732, -0.8036818185326815, -1.6863246768255735, 8.313675323174426, -1.6863246768255735, -1.7386218976054832, 8.261378102394517, -1.7386218976054832, -1.764636437170162, 8.235363562829837, -1.764636437170162, -1.764636437170162, 8.235363562829837, -1.764636437170162, -1.1565751227374246, 8.843424877262576, -1.1565751227374246, -1.897459153329338, 8.102540846670662, -1.897459153329338, -1.764636437170162, 8.235363562829837, -1.764636437170162, -0.1536593968843274, 9.846340603115673, -0.1536593968843274, -1.764636437170162, 8.235363562829837, -1.764636437170162, -2.1730838266985826, 7.826916173301417, -2.1730838266985826, -0.542941529533834, -0.542941529533834, 9.457058470466166, -0.8036818185326815, -0.8036818185326815, 9.19631818146732, -1.6863246768255735, -1.6863246768255735, 8.313675323174426, -1.7386218976054832, -1.7386218976054832, 8.261378102394517, -1.764636437170162, -1.764636437170162, 8.235363562829837, -1.764636437170162, -1.764636437170162, 8.235363562829837, -1.1565751227374246, -1.1565751227374246, 8.843424877262576, -1.897459153329338, -1.897459153329338, 8.102540846670662, -1.764636437170162, -1.764636437170162, 8.235363562829837, -0.1536593968843274, -0.1536593968843274, 9.846340603115673, -1.764636437170162, -1.764636437170162, 8.235363562829837, -2.1730838266985826, -2.1730838266985826, 7.826916173301417, 2.0, 2.0, 9.642859205563035, -0.3571407944369649, -0.3571407944369649, 7.331581081103902, -2.668418918896098, -2.668418918896098, 9.249876915158392, -0.7501230848416083, -0.7501230848416083, 9.747207358988511, -0.2527926410114887, -0.2527926410114887, 7.331581081103902, -2.668418918896098, -2.668418918896098, 8.908481995720482, -1.0915180042795187, -1.0915180042795187, 8.730698655027354, -1.2693013449726465, -1.2693013449726465, 2.0, -0.3571407944369649, 9.642859205563035, -0.3571407944369649, -2.668418918896098, 7.331581081103902, -2.668418918896098, -0.7501230848416083, 9.249876915158392, -0.7501230848416083, -0.2527926410114887, 9.747207358988511, -0.2527926410114887, -2.668418918896098, 7.331581081103902, -2.668418918896098, -1.0915180042795187, 8.908481995720482, -1.0915180042795187, -1.2693013449726465, 8.730698655027354, -1.2693013449726465, -0.3571407944369649, -0.3571407944369649, 9.642859205563035, -2.668418918896098, -2.668418918896098, 7.331581081103902, -0.7501230848416083, -0.7501230848416083, 9.249876915158392, -0.2527926410114887, -0.2527926410114887, 9.747207358988511, -2.668418918896098, -2.668418918896098, 7.331581081103902, -1.0915180042795187, -1.0915180042795187, 8.908481995720482, -1.2693013449726465, -1.2693013449726465, 8.730698655027354, 2.0, 2.0, 9.122556248918265, -0.8774437510817341, -0.8774437510817341, 9.877443751081735, -0.12255624891826589, -0.12255624891826589, 9.401227526556971, -0.5987724734430291, -0.5987724734430291, 7.622556248918266, -2.377443751081734, -2.377443751081734, 8.800532699513468, -1.199467300486531, -1.199467300486531, 9.60375937481971, -0.39624062518028946, -0.39624062518028946, 2.0, -0.8774437510817341, 9.122556248918265, -0.8774437510817341, -0.12255624891826589, 9.877443751081735, -0.12255624891826589, -0.5987724734430291, 9.401227526556971, -0.5987724734430291, -2.377443751081734, 7.622556248918266, -2.377443751081734, -1.199467300486531, 8.800532699513468, -1.199467300486531, -0.39624062518028946, 9.60375937481971, -0.39624062518028946, -0.8774437510817341, -0.8774437510817341, 9.122556248918265, -0.12255624891826589, -0.12255624891826589, 9.877443751081735, -0.5987724734430291, -0.5987724734430291, 9.401227526556971, -2.377443751081734, -2.377443751081734, 7.622556248918266, -1.199467300486531, -1.199467300486531, 8.800532699513468, -0.39624062518028946, -0.39624062518028946, 9.60375937481971, 2.0, 2.0, 10.0, 0.0, 0.0, 6.423088948431735, -3.576911051568265, -3.576911051568265, 7.226315623737976, -2.7736843762620236, -2.7736843762620236, 2.0, 0.0, 10.0, 0.0, -3.576911051568265, 6.423088948431735, -3.576911051568265, -2.7736843762620236, 7.226315623737976, -2.7736843762620236, 0.0, 0.0, 10.0, -3.576911051568265, -3.576911051568265, 6.423088948431735, -2.7736843762620236, -2.7736843762620236, 7.226315623737976, 2.0, 2.0, 6.970576057818619, -3.029423942181382, -3.029423942181382, 6.423088948431735, -3.576911051568265, -3.576911051568265, 2.0, -3.029423942181382, 6.970576057818619, -3.029423942181382, -3.576911051568265, 6.423088948431735, -3.576911051568265, -3.029423942181382, -3.029423942181382, 6.970576057818619, -3.576911051568265, -3.576911051568265, 6.423088948431735, 2.0, 2.0, 6.970576057818619, -3.029423942181382, -3.029423942181382, 6.423088948431735, -3.576911051568265, -3.576911051568265, 2.0, -3.029423942181382, 6.970576057818619, -3.029423942181382, -3.576911051568265, 6.423088948431735, -3.576911051568265, -3.029423942181382, -3.029423942181382, 6.970576057818619, -3.576911051568265, -3.576911051568265, 6.423088948431735, 2.0, 2.0, 7.970576057818619, -2.029423942181382, -2.029423942181382, 7.423088948431735, -2.576911051568265, -2.576911051568265, 7.646759519737388, -2.3532404802626123, -2.3532404802626123, 2.0, -2.029423942181382, 7.970576057818619, -2.029423942181382, -2.576911051568265, 7.423088948431735, -2.576911051568265, -2.3532404802626123, 7.646759519737388, -2.3532404802626123, -2.029423942181382, -2.029423942181382, 7.970576057818619, -2.576911051568265, -2.576911051568265, 7.423088948431735, -2.3532404802626123, -2.3532404802626123, 7.646759519737388, 2.0, 2.0, 6.970576057818619, -3.029423942181382, -3.029423942181382, 6.423088948431735, -3.576911051568265, -3.576911051568265, 6.646759519737388, -3.3532404802626123, -3.3532404802626123, 2.0, -3.029423942181382, 6.970576057818619, -3.029423942181382, -3.576911051568265, 6.423088948431735, -3.576911051568265, -3.3532404802626123, 6.646759519737388, -3.3532404802626123, -3.029423942181382, -3.029423942181382, 6.970576057818619, -3.576911051568265, -3.576911051568265, 6.423088948431735, -3.3532404802626123, -3.3532404802626123, 6.646759519737388, 2.0, 2.0, 9.863454747160649, -0.1365452528393507, -0.1365452528393507, 9.315967637773767, -0.6840323622262341, -0.6840323622262341, 8.10712131065797, -1.892878689342031, -1.892878689342031, 7.107121310657969, -2.892878689342031, -2.892878689342031, 8.025417144712458, -1.9745828552875415, -1.9745828552875415, 9.539638209079419, -0.46036179092058127, -0.46036179092058127, 2.0, -0.1365452528393507, 9.863454747160649, -0.1365452528393507, -0.6840323622262341, 9.315967637773767, -0.6840323622262341, -1.892878689342031, 8.10712131065797, -1.892878689342031, -2.892878689342031, 7.107121310657969, -2.892878689342031, -1.9745828552875415, 8.025417144712458, -1.9745828552875415, -0.46036179092058127, 9.539638209079419, -0.46036179092058127, -0.1365452528393507, -0.1365452528393507, 9.863454747160649, -0.6840323622262341, -0.6840323622262341, 9.315967637773767, -1.892878689342031, -1.892878689342031, 8.10712131065797, -2.892878689342031, -2.892878689342031, 7.107121310657969, -1.9745828552875415, -1.9745828552875415, 8.025417144712458, -0.46036179092058127, -0.46036179092058127, 9.539638209079419, 2.0, 2.0, 9.672217583374177, -0.32778241662582186, -0.32778241662582186, 8.950105827741691, -1.0498941722583082, -1.0498941722583082, 2.0, -0.32778241662582186, 9.672217583374177, -0.32778241662582186, -1.0498941722583082, 8.950105827741691, -1.0498941722583082, -0.32778241662582186, -0.32778241662582186, 9.672217583374177, -1.0498941722583082, -1.0498941722583082, 8.950105827741691, 2.0, 2.0, 10.0, 0.0, 0.0, 10.0, 0.0, 0.0, 2.0, 0.0, 10.0, 0.0, 0.0, 10.0, 0.0, 0.0, 0.0, 10.0, 0.0, 0.0, 10.0, 2.0, 2.0, 10.0, 0.0, 0.0, 2.0, 0.0, 10.0, 0.0, 0.0, 0.0, 10.0, 2.0, 2.0, 10.0, 0.0, 0.0, 2.0, 0.0, 10.0, 0.0, 0.0, 0.0, 10.0, 2.0, 2.0, 8.749387984894238, -1.2506120151057627, -1.2506120151057627, 7.249387984894238, -2.7506120151057627, -2.7506120151057627, 8.249387984894238, -1.7506120151057627, -1.7506120151057627, 7.249387984894238, -2.7506120151057627, -2.7506120151057627, 8.249387984894238, -1.7506120151057627, -1.7506120151057627, 7.249387984894238, -2.7506120151057627, -2.7506120151057627, 8.249387984894238, -1.7506120151057627, -1.7506120151057627, 7.249387984894238, -2.7506120151057627, -2.7506120151057627, 8.249387984894238, -1.7506120151057627, -1.7506120151057627, 7.249387984894238, -2.7506120151057627, -2.7506120151057627, 7.9713160797816, -2.0286839202184, -2.0286839202184, 2.0, -1.2506120151057627, 8.749387984894238, -1.2506120151057627, -2.7506120151057627, 7.249387984894238, -2.7506120151057627, -1.7506120151057627, 8.249387984894238, -1.7506120151057627, -2.7506120151057627, 7.249387984894238, -2.7506120151057627, -1.7506120151057627, 8.249387984894238, -1.7506120151057627, -2.7506120151057627, 7.249387984894238, -2.7506120151057627, -1.7506120151057627, 8.249387984894238, -1.7506120151057627, -2.7506120151057627, 7.249387984894238, -2.7506120151057627, -1.7506120151057627, 8.249387984894238, -1.7506120151057627, -2.7506120151057627, 7.249387984894238, -2.7506120151057627, -2.0286839202184, 7.9713160797816, -2.0286839202184, -1.2506120151057627, -1.2506120151057627, 8.749387984894238, -2.7506120151057627, -2.7506120151057627, 7.249387984894238, -1.7506120151057627, -1.7506120151057627, 8.249387984894238, -2.7506120151057627, -2.7506120151057627, 7.249387984894238, -1.7506120151057627, -1.7506120151057627, 8.249387984894238, -2.7506120151057627, -2.7506120151057627, 7.249387984894238, -1.7506120151057627, -1.7506120151057627, 8.249387984894238, -2.7506120151057627, -2.7506120151057627, 7.249387984894238, -1.7506120151057627, -1.7506120151057627, 8.249387984894238, -2.7506120151057627, -2.7506120151057627, 7.249387984894238, -2.0286839202184, -2.0286839202184, 7.9713160797816, 2.0, 2.0, 9.278071905112638, -0.7219280948873623, -0.7219280948873623, 2.0, -0.7219280948873623, 9.278071905112638, -0.7219280948873623, -0.7219280948873623, -0.7219280948873623, 9.278071905112638, 2.0, 2.0, 8.789222915584933, -1.2107770844150672, -1.2107770844150672, 2.0, -1.2107770844150672, 8.789222915584933, -1.2107770844150672, -1.2107770844150672, -1.2107770844150672, 8.789222915584933, 2.0, 2.0, 9.289222915584933, -0.7107770844150672, -0.7107770844150672, 2.0, -0.7107770844150672, 9.289222915584933, -0.7107770844150672, -0.7107770844150672, -0.7107770844150672, 9.289222915584933, 2.0, 2.0, 7.846988167857295, -2.153011832142705, -2.153011832142705, 6.346988167857295, -3.653011832142705, -3.653011832142705, 9.56696126187927, -0.4330387381207301, -0.4330387381207301, 6.346988167857295, -3.653011832142705, -3.653011832142705, 9.323204392382058, -0.676795607617942, -0.676795607617942, 7.317938762311964, -2.6820612376880364, -2.6820612376880364, 6.346988167857295, -3.653011832142705, -3.653011832142705, 9.492235495647623, -0.5077645043523775, -0.5077645043523775, 7.931950668578451, -2.068049331421549, -2.068049331421549, 7.346988167857295, -2.653011832142705, -2.653011832142705, 6.346988167857295, -3.653011832142705, -3.653011832142705, 9.049443129763207, -0.9505568702367939, -0.9505568702367939, 2.0, -2.153011832142705, 7.846988167857295, -2.153011832142705, -3.653011832142705, 6.346988167857295, -3.653011832142705, -0.4330387381207301, 9.56696126187927, -0.4330387381207301, -3.653011832142705, 6.346988167857295, -3.653011832142705, -0.676795607617942, 9.323204392382058, -0.676795607617942, -2.6820612376880364, 7.317938762311964, -2.6820612376880364, -3.653011832142705, 6.346988167857295, -3.653011832142705, -0.5077645043523775, 9.492235495647623, -0.5077645043523775, -2.068049331421549, 7.931950668578451, -2.068049331421549, -2.653011832142705, 7.346988167857295, -2.653011832142705, -3.653011832142705, 6.346988167857295, -3.653011832142705, -0.9505568702367939, 9.049443129763207, -0.9505568702367939, -2.153011832142705, -2.153011832142705, 7.846988167857295, -3.653011832142705, -3.653011832142705, 6.346988167857295, -0.4330387381207301, -0.4330387381207301, 9.56696126187927, -3.653011832142705, -3.653011832142705, 6.346988167857295, -0.676795607617942, -0.676795607617942, 9.323204392382058, -2.6820612376880364, -2.6820612376880364, 7.317938762311964, -3.653011832142705, -3.653011832142705, 6.346988167857295, -0.5077645043523775, -0.5077645043523775, 9.492235495647623, -2.068049331421549, -2.068049331421549, 7.931950668578451, -2.653011832142705, -2.653011832142705, 7.346988167857295, -3.653011832142705, -3.653011832142705, 6.346988167857295, -0.9505568702367939, -0.9505568702367939, 9.049443129763207, 2.0, 2.0, 7.023783775475237, -2.976216224524763, -2.976216224524763, 7.297545038094089, -2.7024549619059113, -2.7024549619059113, 2.0, -2.976216224524763, 7.023783775475237, -2.976216224524763, -2.7024549619059113, 7.297545038094089, -2.7024549619059113, -2.976216224524763, -2.976216224524763, 7.023783775475237, -2.7024549619059113, -2.7024549619059113, 7.297545038094089, 2.0, 2.0, 9.523783775475238, -0.4762162245247632, -0.4762162245247632, 9.79754503809409, -0.20245496190591128, -0.20245496190591128, 2.0, -0.4762162245247632, 9.523783775475238, -0.4762162245247632, -0.20245496190591128, 9.79754503809409, -0.20245496190591128, -0.4762162245247632, -0.4762162245247632, 9.523783775475238, -0.20245496190591128, -0.20245496190591128, 9.79754503809409, 2.0, 2.0, 8.523783775475238, -1.4762162245247632, -1.4762162245247632, 2.0, -1.4762162245247632, 8.523783775475238, -1.4762162245247632, -1.4762162245247632, -1.4762162245247632, 8.523783775475238, 2.0, 2.0, 7.5, -2.5, -2.5, 9.426482637085998, -0.5735173629140013, -0.5735173629140013, 9.564559799051002, -0.43544020094899816, -0.43544020094899816, 2.0, -2.5, 7.5, -2.5, -0.5735173629140013, 9.426482637085998, -0.5735173629140013, -0.43544020094899816, 9.564559799051002, -0.43544020094899816, -2.5, -2.5, 7.5, -0.5735173629140013, -0.5735173629140013, 9.426482637085998, -0.43544020094899816, -0.43544020094899816, 9.564559799051002, 2.0, 2.0, 6.926482637085998, -3.0735173629140013, -3.0735173629140013, 10.0, 0.0, 0.0, 2.0, -3.0735173629140013, 6.926482637085998, -3.0735173629140013, 0.0, 10.0, 0.0, -3.0735173629140013, -3.0735173629140013, 6.926482637085998, 0.0, 0.0, 10.0, 2.0, 2.0, 9.51223923845487, -0.48776076154513115, -0.48776076154513115, 6.4387218755408675, -3.5612781244591325, -3.5612781244591325, 6.4387218755408675, -3.5612781244591325, -3.5612781244591325, 6.4387218755408675, -3.5612781244591325, -3.5612781244591325, 9.899182533959632, -0.10081746604036734, -0.10081746604036734, 2.0, -0.48776076154513115, 9.51223923845487, -0.48776076154513115, -3.5612781244591325, 6.4387218755408675, -3.5612781244591325, -3.5612781244591325, 6.4387218755408675, -3.5612781244591325, -3.5612781244591325, 6.4387218755408675, -3.5612781244591325, -0.10081746604036734, 9.899182533959632, -0.10081746604036734, -0.48776076154513115, -0.48776076154513115, 9.51223923845487, -3.5612781244591325, -3.5612781244591325, 6.4387218755408675, -3.5612781244591325, -3.5612781244591325, 6.4387218755408675, -3.5612781244591325, -3.5612781244591325, 6.4387218755408675, -0.10081746604036734, -0.10081746604036734, 9.899182533959632, 2.0, 2.0, 7.0983484109638235, -2.9016515890361765, -2.9016515890361765, 6.3379044095005, -3.6620955904995, -3.6620955904995, 2.0, -2.9016515890361765, 7.0983484109638235, -2.9016515890361765, -3.6620955904995, 6.3379044095005, -3.6620955904995, -2.9016515890361765, -2.9016515890361765, 7.0983484109638235, -3.6620955904995, -3.6620955904995, 6.3379044095005, 2.0, 2.0, 9.901651589036177, -0.09834841096382352, -0.09834841096382352, 7.0, -3.0, -3.0, 9.983174358907977, -0.016825641092022448, -0.016825641092022448, 9.3379044095005, -0.6620955904994998, -0.6620955904994998, 2.0, -0.09834841096382352, 9.901651589036177, -0.09834841096382352, -3.0, 7.0, -3.0, -0.016825641092022448, 9.983174358907977, -0.016825641092022448, -0.6620955904994998, 9.3379044095005, -0.6620955904994998, -0.09834841096382352, -0.09834841096382352, 9.901651589036177, -3.0, -3.0, 7.0, -0.016825641092022448, -0.016825641092022448, 9.983174358907977, -0.6620955904994998, -0.6620955904994998, 9.3379044095005, 2.0, 2.0, 6.983174358907977, -3.0168256410920224, -3.0168256410920224, 6.3379044095005, -3.6620955904995, -3.6620955904995, 2.0, -3.0168256410920224, 6.983174358907977, -3.0168256410920224, -3.6620955904995, 6.3379044095005, -3.6620955904995, -3.0168256410920224, -3.0168256410920224, 6.983174358907977, -3.6620955904995, -3.6620955904995, 6.3379044095005, 2.0, 2.0, 7.770733793640592, -2.2292662063594078, -2.2292662063594078, 7.718436572860683, -2.281563427139317, -2.281563427139317, 8.778305092363672, -1.221694907636328, -1.221694907636328, 8.778305092363672, -1.221694907636328, -1.221694907636328, 7.559599317136828, -2.4404006828631717, -2.4404006828631717, 8.778305092363672, -1.221694907636328, -1.221694907636328, 9.303399073581838, -0.6966009264181614, -0.6966009264181614, 8.778305092363672, -1.221694907636328, -1.221694907636328, 7.283974643767584, -2.716025356232416, -2.716025356232416, 2.0, -2.2292662063594078, 7.770733793640592, -2.2292662063594078, -2.281563427139317, 7.718436572860683, -2.281563427139317, -1.221694907636328, 8.778305092363672, -1.221694907636328, -1.221694907636328, 8.778305092363672, -1.221694907636328, -2.4404006828631717, 7.559599317136828, -2.4404006828631717, -1.221694907636328, 8.778305092363672, -1.221694907636328, -0.6966009264181614, 9.303399073581838, -0.6966009264181614, -1.221694907636328, 8.778305092363672, -1.221694907636328, -2.716025356232416, 7.283974643767584, -2.716025356232416, -2.2292662063594078, -2.2292662063594078, 7.770733793640592, -2.281563427139317, -2.281563427139317, 7.718436572860683, -1.221694907636328, -1.221694907636328, 8.778305092363672, -1.221694907636328, -1.221694907636328, 8.778305092363672, -2.4404006828631717, -2.4404006828631717, 7.559599317136828, -1.221694907636328, -1.221694907636328, 8.778305092363672, -0.6966009264181614, -0.6966009264181614, 9.303399073581838, -1.221694907636328, -1.221694907636328, 8.778305092363672, -2.716025356232416, -2.716025356232416, 7.283974643767584, 2.0, 2.0, 9.647106695795257, -0.3528933042047431, -0.3528933042047431, 8.6305979918341, -1.3694020081659009, -1.3694020081659009, 2.0, -0.3528933042047431, 9.647106695795257, -0.3528933042047431, -1.3694020081659009, 8.6305979918341, -1.3694020081659009, -0.3528933042047431, -0.3528933042047431, 9.647106695795257, -1.3694020081659009, -1.3694020081659009, 8.6305979918341, 2.0, 2.0, 9.390066564551546, -0.6099334354484536, -0.6099334354484536, 8.373557860590388, -1.6264421394096114, -1.6264421394096114, 2.0, -0.6099334354484536, 9.390066564551546, -0.6099334354484536, -1.6264421394096114, 8.373557860590388, -1.6264421394096114, -0.6099334354484536, -0.6099334354484536, 9.390066564551546, -1.6264421394096114, -1.6264421394096114, 8.373557860590388, 2.0, 2.0, 8.523783775475238, -1.4762162245247632, -1.4762162245247632, 2.0, -1.4762162245247632, 8.523783775475238, -1.4762162245247632, -1.4762162245247632, -1.4762162245247632, 8.523783775475238, 2.0, 2.0, 10.0, 0.0, 0.0, 6.062279736131256, -3.9377202638687443, -3.9377202638687443, 2.0, 0.0, 10.0, 0.0, -3.9377202638687443, 6.062279736131256, -3.9377202638687443, 0.0, 0.0, 10.0, -3.9377202638687443, -3.9377202638687443, 6.062279736131256, 2.0, 2.0, 9.65860508056209, -0.34139491943791045, -0.34139491943791045, 7.980575570185746, -2.0194244298142547, -2.0194244298142547, 2.0, -0.34139491943791045, 9.65860508056209, -0.34139491943791045, -2.0194244298142547, 7.980575570185746, -2.0194244298142547, -0.34139491943791045, -0.34139491943791045, 9.65860508056209, -2.0194244298142547, -2.0194244298142547, 7.980575570185746, 2.0, 2.0, 7.5, -2.5, -2.5, 8.923088948431735, -1.0769110515682652, -1.0769110515682652, 9.726315623737976, -0.2736843762620236, -0.2736843762620236, 2.0, -2.5, 7.5, -2.5, -1.0769110515682652, 8.923088948431735, -1.0769110515682652, -0.2736843762620236, 9.726315623737976, -0.2736843762620236, -2.5, -2.5, 7.5, -1.0769110515682652, -1.0769110515682652, 8.923088948431735, -0.2736843762620236, -0.2736843762620236, 9.726315623737976, 2.0, 2.0, 6.423088948431735, -3.576911051568265, -3.576911051568265, 7.226315623737976, -2.7736843762620236, -2.7736843762620236, 2.0, -3.576911051568265, 6.423088948431735, -3.576911051568265, -2.7736843762620236, 7.226315623737976, -2.7736843762620236, -3.576911051568265, -3.576911051568265, 6.423088948431735, -2.7736843762620236, -2.7736843762620236, 7.226315623737976, 2.0, 2.0, 9.452512890613116, -0.5474871093868834, -0.5474871093868834, 7.970576057818619, -2.029423942181382, -2.029423942181382, 6.970576057818619, -3.029423942181382, -3.029423942181382, 7.888871891873108, -2.1111281081268922, -2.1111281081268922, 9.67618346191877, -0.32381653808123056, -0.32381653808123056, 2.0, -0.5474871093868834, 9.452512890613116, -0.5474871093868834, -2.029423942181382, 7.970576057818619, -2.029423942181382, -3.029423942181382, 6.970576057818619, -3.029423942181382, -2.1111281081268922, 7.888871891873108, -2.1111281081268922, -0.32381653808123056, 9.67618346191877, -0.32381653808123056, -0.5474871093868834, -0.5474871093868834, 9.452512890613116, -2.029423942181382, -2.029423942181382, 7.970576057818619, -3.029423942181382, -3.029423942181382, 6.970576057818619, -2.1111281081268922, -2.1111281081268922, 7.888871891873108, -0.32381653808123056, -0.32381653808123056, 9.67618346191877, 2.0, 2.0, 10.0, 0.0, 0.0, 6.646759519737388, -3.3532404802626123, -3.3532404802626123, 2.0, 0.0, 10.0, 0.0, -3.3532404802626123, 6.646759519737388, -3.3532404802626123, 0.0, 0.0, 10.0, -3.3532404802626123, -3.3532404802626123, 6.646759519737388, 2.0, 2.0, 9.485252437695438, -0.5147475623045619, -0.5147475623045619, 9.914222361021654, -0.085777638978346, -0.085777638978346, 2.0, -0.5147475623045619, 9.485252437695438, -0.5147475623045619, -0.085777638978346, 9.914222361021654, -0.085777638978346, -0.5147475623045619, -0.5147475623045619, 9.485252437695438, -0.085777638978346, -0.085777638978346, 9.914222361021654, 2.0, 2.0, 7.2472847210202955, -2.7527152789797045, -2.7527152789797045, 6.646759519737388, -3.3532404802626123, -3.3532404802626123, 2.0, -2.7527152789797045, 7.2472847210202955, -2.7527152789797045, -3.3532404802626123, 6.646759519737388, -3.3532404802626123, -2.7527152789797045, -2.7527152789797045, 7.2472847210202955, -3.3532404802626123, -3.3532404802626123, 6.646759519737388, 2.0, 2.0, 8.289814075880773, -1.7101859241192259, -1.7101859241192259, 8.083426001654075, -1.916573998345925, -1.916573998345925, 8.563333518083313, -1.4366664819166874, -1.4366664819166874, 9.518370647862199, -0.4816293521378019, -0.4816293521378019, 8.563333518083313, -1.4366664819166874, -1.4366664819166874, 7.567702320248288, -2.432297679751712, -2.432297679751712, 2.0, -1.7101859241192259, 8.289814075880773, -1.7101859241192259, -1.916573998345925, 8.083426001654075, -1.916573998345925, -1.4366664819166874, 8.563333518083313, -1.4366664819166874, -0.4816293521378019, 9.518370647862199, -0.4816293521378019, -1.4366664819166874, 8.563333518083313, -1.4366664819166874, -2.432297679751712, 7.567702320248288, -2.432297679751712, -1.7101859241192259, -1.7101859241192259, 8.289814075880773, -1.916573998345925, -1.916573998345925, 8.083426001654075, -1.4366664819166874, -1.4366664819166874, 8.563333518083313, -0.4816293521378019, -0.4816293521378019, 9.518370647862199, -1.4366664819166874, -1.4366664819166874, 8.563333518083313, -2.432297679751712, -2.432297679751712, 7.567702320248288, 2.0, 2.0, 9.793611925773302, -0.20638807422669903, -0.20638807422669903, 6.853147593964087, -3.1468524060359133, -3.1468524060359133, 8.771443428018577, -1.228556571981424, -1.228556571981424, 6.853147593964087, -3.1468524060359133, -3.1468524060359133, 9.277888244367514, -0.7221117556324863, -0.7221117556324863, 2.0, -0.20638807422669903, 9.793611925773302, -0.20638807422669903, -3.1468524060359133, 6.853147593964087, -3.1468524060359133, -1.228556571981424, 8.771443428018577, -1.228556571981424, -3.1468524060359133, 6.853147593964087, -3.1468524060359133, -0.7221117556324863, 9.277888244367514, -0.7221117556324863, -0.20638807422669903, -0.20638807422669903, 9.793611925773302, -3.1468524060359133, -3.1468524060359133, 6.853147593964087, -1.228556571981424, -1.228556571981424, 8.771443428018577, -3.1468524060359133, -3.1468524060359133, 6.853147593964087, -0.7221117556324863, -0.7221117556324863, 9.277888244367514, 2.0, 2.0, 10.0, 0.0, 0.0, 2.0, 0.0, 10.0, 0.0, 0.0, 0.0, 10.0, 2.0, 2.0, 2.0, 2.0, 2.0, 2.0, 2.0, 2.0, 2.0, 2.0, 2.0, 2.0, 2.0, 2.0, 2.0, 2.0, 2.0, 2.0, 2.0, 2.0, 2.0, 2.0, 2.0, 2.0, 2.0, 2.0, 9.726238737381149, -0.2737612626188519, -0.2737612626188519, 7.023783775475237, -2.976216224524763, -2.976216224524763, 2.0, -0.2737612626188519, 9.726238737381149, -0.2737612626188519, -2.976216224524763, 7.023783775475237, -2.976216224524763, -0.2737612626188519, -0.2737612626188519, 9.726238737381149, -2.976216224524763, -2.976216224524763, 7.023783775475237, 2.0, 2.0, 2.0, 2.0, 2.0, 7.6359883704795735, -2.364011629520427, -2.364011629520427, 2.0, -2.364011629520427, 7.6359883704795735, -2.364011629520427, -2.364011629520427, -2.364011629520427, 7.6359883704795735, 2.0, 2.0, 2.0, 2.0, 2.0, 2.0, 2.0, 2.0, 7.750977500432693, -2.2490224995673067, -2.2490224995673067, 6.7800269059780245, -3.219973094021975, -3.219973094021975, 9.925274233768352, -0.0747257662316474, -0.0747257662316474, 8.36498940669918, -1.635010593300819, -1.635010593300819, 7.7800269059780245, -2.219973094021975, -2.219973094021975, 2.0, -2.2490224995673067, 7.750977500432693, -2.2490224995673067, -3.219973094021975, 6.7800269059780245, -3.219973094021975, -0.0747257662316474, 9.925274233768352, -0.0747257662316474, -1.635010593300819, 8.36498940669918, -1.635010593300819, -2.219973094021975, 7.7800269059780245, -2.219973094021975, -2.2490224995673067, -2.2490224995673067, 7.750977500432693, -3.219973094021975, -3.219973094021975, 6.7800269059780245, -0.0747257662316474, -0.0747257662316474, 9.925274233768352, -1.635010593300819, -1.635010593300819, 8.36498940669918, -2.219973094021975, -2.219973094021975, 7.7800269059780245, 2.0, 2.0, 10.0, 0.0, 0.0, 2.0, 0.0, 10.0, 0.0, 0.0, 0.0, 10.0, 2.0, 2.0, 9.726238737381149, -0.2737612626188519, -0.2737612626188519, 7.023783775475237, -2.976216224524763, -2.976216224524763, 2.0, -0.2737612626188519, 9.726238737381149, -0.2737612626188519, -2.976216224524763, 7.023783775475237, -2.976216224524763, -0.2737612626188519, -0.2737612626188519, 9.726238737381149, -2.976216224524763, -2.976216224524763, 7.023783775475237, 2.0, 2.0, 2.0, 2.0, 2.0, 9.861922838034996, -0.1380771619650032, -0.1380771619650032, 6.926482637085998, -3.0735173629140013, -3.0735173629140013, 7.844778471140488, -2.155221528859512, -2.155221528859512, 6.926482637085998, -3.0735173629140013, -3.0735173629140013, 2.0, -0.1380771619650032, 9.861922838034996, -0.1380771619650032, -3.0735173629140013, 6.926482637085998, -3.0735173629140013, -2.155221528859512, 7.844778471140488, -2.155221528859512, -3.0735173629140013, 6.926482637085998, -3.0735173629140013, -0.1380771619650032, -0.1380771619650032, 9.861922838034996, -3.0735173629140013, -3.0735173629140013, 6.926482637085998, -2.155221528859512, -2.155221528859512, 7.844778471140488, -3.0735173629140013, -3.0735173629140013, 6.926482637085998, 2.0, 2.0, 6.3379044095005, -3.6620955904995, -3.6620955904995, 2.0, -3.6620955904995, 6.3379044095005, -3.6620955904995, -3.6620955904995, -3.6620955904995, 6.3379044095005, 2.0, 2.0, 2.0, 2.0, 2.0, 6.3379044095005, -3.6620955904995, -3.6620955904995, 2.0, -3.6620955904995, 6.3379044095005, -3.6620955904995, -3.6620955904995, -3.6620955904995, 6.3379044095005, 2.0, 2.0, 6.3379044095005, -3.6620955904995, -3.6620955904995, 2.0, -3.6620955904995, 6.3379044095005, -3.6620955904995, -3.6620955904995, -3.6620955904995, 6.3379044095005, 2.0, 2.0, 9.239555998536677, -0.7604440014633234, -0.7604440014633234, 2.0, -0.7604440014633234, 9.239555998536677, -0.7604440014633234, -0.7604440014633234, -0.7604440014633234, 9.239555998536677, 2.0, 2.0, 6.3379044095005, -3.6620955904995, -3.6620955904995, 2.0, -3.6620955904995, 6.3379044095005, -3.6620955904995, -3.6620955904995, -3.6620955904995, 6.3379044095005, 2.0, 2.0, 9.354730050592522, -0.6452699494074774, -0.6452699494074774, 2.0, -0.6452699494074774, 9.354730050592522, -0.6452699494074774, -0.6452699494074774, -0.6452699494074774, 9.354730050592522, 2.0, 2.0, 6.3379044095005, -3.6620955904995, -3.6620955904995, 2.0, -3.6620955904995, 6.3379044095005, -3.6620955904995, -3.6620955904995, -3.6620955904995, 6.3379044095005, 2.0, 2.0, 9.788865523496236, -0.21113447650376438, -0.21113447650376438, 6.549038886004265, -3.4509611139957355, -3.4509611139957355, 8.467334720058753, -1.5326652799412461, -1.5326652799412461, 2.0, -0.21113447650376438, 9.788865523496236, -0.21113447650376438, -3.4509611139957355, 6.549038886004265, -3.4509611139957355, -1.5326652799412461, 8.467334720058753, -1.5326652799412461, -0.21113447650376438, -0.21113447650376438, 9.788865523496236, -3.4509611139957355, -3.4509611139957355, 6.549038886004265, -1.5326652799412461, -1.5326652799412461, 8.467334720058753, 2.0, 2.0, 6.496741665224355, -3.503258334775645, -3.503258334775645, 9.5655380709069, -0.4344619290930991, -0.4344619290930991, 2.0, -3.503258334775645, 6.496741665224355, -3.503258334775645, -0.4344619290930991, 9.5655380709069, -0.4344619290930991, -3.503258334775645, -3.503258334775645, 6.496741665224355, -0.4344619290930991, -0.4344619290930991, 9.5655380709069, 2.0, 2.0, 6.062279736131256, -3.9377202638687443, -3.9377202638687443, 2.0, -3.9377202638687443, 6.062279736131256, -3.9377202638687443, -3.9377202638687443, -3.9377202638687443, 6.062279736131256, 2.0, 2.0, 6.062279736131256, -3.9377202638687443, -3.9377202638687443, 2.0, -3.9377202638687443, 6.062279736131256, -3.9377202638687443, -3.9377202638687443, -3.9377202638687443, 6.062279736131256, 2.0, 2.0, 9.196773324693758, -0.8032266753062416, -0.8032266753062416, 6.423088948431735, -3.576911051568265, -3.576911051568265, 9.776329428694346, -0.22367057130565282, -0.22367057130565282, 2.0, -0.8032266753062416, 9.196773324693758, -0.8032266753062416, -3.576911051568265, 6.423088948431735, -3.576911051568265, -0.22367057130565282, 9.776329428694346, -0.22367057130565282, -0.8032266753062416, -0.8032266753062416, 9.196773324693758, -3.576911051568265, -3.576911051568265, 6.423088948431735, -0.22367057130565282, -0.22367057130565282, 9.776329428694346, 2.0, 2.0, 8.983491296038842, -1.0165087039611578, -1.0165087039611578, 2.0, -1.0165087039611578, 8.983491296038842, -1.0165087039611578, -1.0165087039611578, -1.0165087039611578, 8.983491296038842, 2.0, 2.0, 6.062279736131256, -3.9377202638687443, -3.9377202638687443, 2.0, -3.9377202638687443, 6.062279736131256, -3.9377202638687443, -3.9377202638687443, -3.9377202638687443, 6.062279736131256, 2.0, 2.0, 7.639180650747835, -2.360819349252165, -2.360819349252165, 2.0, -2.360819349252165, 7.639180650747835, -2.360819349252165, -2.360819349252165, -2.360819349252165, 7.639180650747835, 2.0, 2.0, 7.646759519737388, -2.3532404802626123, -2.3532404802626123, 2.0, -2.3532404802626123, 7.646759519737388, -2.3532404802626123, -2.3532404802626123, -2.3532404802626123, 7.646759519737388, 2.0, 2.0, 6.646759519737388, -3.3532404802626123, -3.3532404802626123, 2.0, -3.3532404802626123, 6.646759519737388, -3.3532404802626123, -3.3532404802626123, -3.3532404802626123, 6.646759519737388, 2.0, 2.0, 7.565055353791877, -2.434944646208123, -2.434944646208123, 2.0, -2.434944646208123, 7.565055353791877, -2.434944646208123, -2.434944646208123, -2.434944646208123, 7.565055353791877, 2.0, 2.0, 6.646759519737388, -3.3532404802626123, -3.3532404802626123, 2.0, -3.3532404802626123, 6.646759519737388, -3.3532404802626123, -3.3532404802626123, -3.3532404802626123, 6.646759519737388, 2.0, 2.0, 9.399474798717092, -0.6005252012829079, -0.6005252012829079, 2.0, -0.6005252012829079, 9.399474798717092, -0.6005252012829079, -0.6005252012829079, -0.6005252012829079, 9.399474798717092, 2.0, 2.0, 6.646759519737388, -3.3532404802626123, -3.3532404802626123, 2.0, -3.3532404802626123, 6.646759519737388, -3.3532404802626123, -3.3532404802626123, -3.3532404802626123, 6.646759519737388, 2.0, 2.0, 2.0, 2.0, 2.0, 2.0, 2.0, 2.0, 2.0, 2.0, 2.0, 2.0, 2.0, 2.0, 2.0, 2.0, 2.0, 2.0, 2.0, 2.0, 2.0, 2.0, 2.0, 2.0, 2.0, 2.0, 2.0, 2.0, 2.0, 2.0, 2.0, 2.0, 2.0, 2.0, 2.0, 2.0, 2.0, 2.0, 2.0, 2.0, 2.0, 2.0, 2.0, 2.0, 2.0, 2.0, 2.0, 2.0, 2.0, 2.0, 2.0, 2.0, 2.0, 2.0, 2.0, 2.0, 2.0, 2.0, 2.0, 2.0, 2.0, 2.0, 2.0, 2.0, 2.0, 2.0, 2.0, 2.0, 2.0, 2.0, 2.0, 2.0, 2.0, 2.0, 2.0, 2.0, 2.0, 2.0, 2.0, 2.0, 2.0, 2.0, 2.0, 2.0, 2.0, 2.0, 2.0, 2.0, 2.0, 2.0, 2.0, 2.0, 2.0, 2.0, 2.0, 2.0, 2.0, 2.0, 2.0, 2.0, 2.0, 2.0, 2.0, 2.0, 2.0, 2.0, 2.0, 2.0, 2.0, 2.0, 2.0, 2.0, 2.0, 2.0, 2.0, 2.0, 2.0], "quadratic_head": [0, 0, 0, 0, 0, 0, 0, 0, 0, 0, 0, 0, 0, 0, 1, 1, 1, 1, 1, 1, 1, 1, 1, 1, 1, 1, 1, 2, 2, 2, 2, 2, 2, 2, 2, 2, 2, 2, 2, 3, 3, 3, 3, 3, 3, 3, 3, 4, 4, 4, 4, 4, 4, 4, 5, 5, 5, 5, 5, 5, 6, 6, 6, 6, 6, 6, 6, 6, 7, 7, 7, 7, 7, 7, 7, 8, 8, 8, 8, 8, 8, 9, 9, 9, 9, 9, 9, 9, 9, 9, 9, 9, 10, 10, 10, 10, 10, 10, 10, 10, 10, 10, 11, 11, 11, 11, 11, 11, 11, 11, 11, 12, 12, 12, 12, 12, 12, 12, 12, 12, 12, 12, 13, 13, 13, 13, 13, 13, 13, 13, 13, 13, 14, 14, 14, 14, 14, 14, 14, 14, 14, 15, 15, 15, 15, 15, 15, 15, 15, 15, 15, 15, 15, 15, 15, 15, 15, 15, 15, 15, 15, 15, 15, 15, 16, 16, 16, 16, 16, 16, 16, 16, 16, 16, 16, 16, 16, 16, 16, 16, 16, 16, 16, 16, 16, 16, 17, 17, 17, 17, 17, 17, 17, 17, 17, 17, 17, 17, 17, 17, 17, 17, 17, 17, 17, 17, 17, 18, 18, 18, 18, 18, 18, 18, 18, 18, 18, 18, 19, 19, 19, 19, 19, 19, 19, 19, 19, 19, 20, 20, 20, 20, 20, 20, 20, 20, 20, 21, 21, 21, 21, 21, 21, 21, 21, 21, 21, 21, 22, 22, 22, 22, 22, 22, 22, 22, 22, 22, 23, 23, 23, 23, 23, 23, 23, 23, 23, 24, 24, 24, 24, 24, 24, 24, 24, 25, 25, 25, 25, 25, 25, 25, 26, 26, 26, 26, 26, 26, 27, 27, 27, 27, 27, 27, 27, 27, 28, 28, 28, 28, 28, 28, 28, 29, 29, 29, 29, 29, 29, 30, 30, 30, 30, 30, 30, 30, 30, 30, 30, 30, 31, 31, 31, 31, 31, 31, 31, 31, 31, 31, 32, 32, 32, 32, 32, 32, 32, 32, 32, 33, 33, 33, 33, 33, 33, 33, 33, 33, 33, 33, 33, 33, 33, 33, 33, 33, 33, 33, 33, 33, 33, 33, 33, 33, 33, 33, 33, 33, 33, 33, 33, 33, 33, 33, 33, 33, 33, 34, 34, 34, 34, 34, 34, 34, 34, 34, 34, 34, 34, 34, 34, 34, 34, 34, 34, 34, 34, 34, 34, 34, 34, 34, 34, 34, 34, 34, 34, 34, 34, 34, 34, 34, 34, 34, 35, 35, 35, 35, 35, 35, 35, 35, 35, 35, 35, 35, 35, 35, 35, 35, 35, 35, 35, 35, 35, 35, 35, 35, 35, 35, 35, 35, 35, 35, 35, 35, 35, 35, 35, 35, 36, 36, 36, 36, 36, 36, 36, 36, 36, 36, 36, 36, 36, 36, 36, 36, 36, 37, 37, 37, 37, 37, 37, 37, 37, 37, 37, 37, 37, 37, 37, 37, 37, 38, 38, 38, 38, 38, 38, 38, 38, 38, 38, 38, 38, 38, 38, 38, 39, 39, 39, 39, 39, 39, 39, 39, 40, 40, 40, 40, 40, 40, 40, 41, 41, 41, 41, 41, 41, 42, 42, 42, 42, 42, 42, 42, 42, 42, 42, 42, 42, 42, 42, 42, 42, 42, 42, 42, 42, 42, 42, 42, 43, 43, 43, 43, 43, 43, 43, 43, 43, 43, 43, 43, 43, 43, 43, 43, 43, 43, 43, 43, 43, 43, 44, 44, 44, 44, 44, 44, 44, 44, 44, 44, 44, 44, 44, 44, 44, 44, 44, 44, 44, 44, 44, 45, 45, 45, 45, 45, 45, 45, 45, 45, 45, 45, 46, 46, 46, 46, 46, 46, 46, 46, 46, 46, 47, 47, 47, 47, 47, 47, 47, 47, 47, 48, 48, 48, 48, 48, 48, 48, 48, 48, 48, 48, 48, 48, 48, 48, 48, 48, 49, 49, 49, 49, 49, 49, 49, 49, 49, 49, 49, 49, 49, 49, 49, 49, 50, 50, 50, 50, 50, 50, 50, 50, 50, 50, 50, 50, 50, 50, 50, 51, 51, 51, 51, 51, 51, 51, 51, 51, 51, 51, 51, 51, 51, 51, 51, 51, 52, 52, 52, 52, 52, 52, 52, 52, 52, 52, 52, 52, 52, 52, 52, 52, 53, 53, 53, 53, 53, 53, 53, 53, 53, 53, 53, 53, 53, 53, 53, 54, 54, 54, 54, 54, 54, 54, 54, 54, 54, 54, 55, 55, 55, 55, 55, 55, 55, 55, 55, 55, 56, 56, 56, 56, 56, 56, 56, 56, 56, 57, 57, 57, 57, 57, 57, 57, 57, 57, 57, 57, 57, 57, 57, 57, 57, 57, 57, 57, 57, 58, 58, 58, 58, 58, 58, 58, 58, 58, 58, 58, 58, 58, 58, 58, 58, 58, 58, 58, 59, 59, 59, 59, 59, 59, 59, 59, 59, 59, 59, 59, 59, 59, 59, 59, 59, 59, 60, 60, 60, 60, 60, 60, 60, 60, 60, 60, 60, 61, 61, 61, 61, 61, 61, 61, 61, 61, 61, 62, 62, 62, 62, 62, 62, 62, 62, 62, 63, 63, 63, 63, 63, 63, 63, 63, 63, 63, 63, 64, 64, 64, 64, 64, 64, 64, 64, 64, 64, 65, 65, 65, 65, 65, 65, 65, 65, 65, 66, 66, 66, 66, 66, 66, 66, 66, 67, 67, 67, 67, 67, 67, 67, 68, 68, 68, 68, 68, 68, 69, 69, 69, 69, 69, 69, 69, 69, 69, 69, 69, 70, 70, 70, 70, 70, 70, 70, 70, 70, 70, 71, 71, 71, 71, 71, 71, 71, 71, 71, 72, 72, 72, 72, 72, 72, 72, 72, 72, 72, 72, 73, 73, 73, 73, 73, 73, 73, 73, 73, 73, 74, 74, 74, 74, 74, 74, 74, 74, 74, 75, 75, 75, 75, 75, 75, 75, 75, 75, 75, 75, 76, 76, 76, 76, 76, 76, 76, 76, 76, 76, 77, 77, 77, 77, 77, 77, 77, 77, 77, 78, 78, 78, 78, 78, 78, 78, 78, 78, 78, 78, 79, 79, 79, 79, 79, 79, 79, 79, 79, 79, 80, 80, 80, 80, 80, 80, 80, 80, 80, 81, 81, 81, 81, 81, 81, 81, 81, 81, 81, 81, 81, 81, 81, 82, 82, 82, 82, 82, 82, 82, 82, 82, 82, 82, 82, 82, 83, 83, 83, 83, 83, 83, 83, 83, 83, 83, 83, 83, 84, 84, 84, 84, 84, 84, 84, 84, 84, 84, 84, 85, 85, 85, 85, 85, 85, 85, 85, 85, 85, 86, 86, 86, 86, 86, 86, 86, 86, 86, 87, 87, 87, 87, 87, 87, 87, 87, 87, 87, 87, 88, 88, 88, 88, 88, 88, 88, 88, 88, 88, 89, 89, 89, 89, 89, 89, 89, 89, 89, 90, 90, 90, 90, 90, 90, 90, 90, 90, 90, 90, 90, 90, 90, 90, 90, 90, 90, 90, 90, 90, 90, 90, 90, 90, 90, 90, 90, 90, 90, 90, 90, 90, 90, 90, 90, 90, 90, 91, 91, 91, 91, 91, 91, 91, 91, 91, 91, 91, 91, 91, 91, 91, 91, 91, 91, 91, 91, 91, 91, 91, 91, 91, 91, 91, 91, 91, 91, 91, 91, 91, 91, 91, 91, 91, 92, 92, 92, 92, 92, 92, 92, 92, 92, 92, 92, 92, 92, 92, 92, 92, 92, 92, 92, 92, 92, 92, 92, 92, 92, 92, 92, 92, 92, 92, 92, 92, 92, 92, 92, 92, 93, 93, 93, 93, 93, 93, 93, 93, 93, 93, 93, 93, 93, 93, 93, 93, 93, 93, 93, 93, 93, 93, 93, 94, 94, 94, 94, 94, 94, 94, 94, 94, 94, 94, 94, 94, 94, 94, 94, 94, 94, 94, 94, 94, 94, 95, 95, 95, 95, 95, 95, 95, 95, 95, 95, 95, 95, 95, 95, 95, 95, 95, 95, 95, 95, 95, 96, 96, 96, 96, 96, 96, 96, 96, 96, 96, 96, 96, 96, 96, 96, 96, 96, 96, 96, 96, 97, 97, 97, 97, 97, 97, 97, 97, 97, 97, 97, 97, 97, 97, 97, 97, 97, 97, 97, 98, 98, 98, 98, 98, 98, 98, 98, 98, 98, 98, 98, 98, 98, 98, 98, 98, 98, 99, 99, 99, 99, 99, 99, 99, 99, 99, 99, 99, 100, 100, 100, 100, 100, 100, 100, 100, 100, 100, 101, 101, 101, 101, 101, 101, 101, 101, 101, 102, 102, 102, 102, 102, 102, 102, 102, 103, 103, 103, 103, 103, 103, 103, 104, 104, 104, 104, 104, 104, 105, 105, 105, 105, 105, 105, 105, 105, 106, 106, 106, 106, 106, 106, 106, 107, 107, 107, 107, 107, 107, 108, 108, 108, 108, 108, 108, 108, 108, 108, 108, 108, 109, 109, 109, 109, 109, 109, 109, 109, 109, 109, 110, 110, 110, 110, 110, 110, 110, 110, 110, 111, 111, 111, 111, 111, 111, 111, 111, 111, 111, 111, 112, 112, 112, 112, 112, 112, 112, 112, 112, 112, 113, 113, 113, 113, 113, 113, 113, 113, 113, 114, 114, 114, 114, 114, 114, 114, 114, 114, 114, 114, 114, 114, 114, 114, 114, 114, 114, 114, 114, 115, 115, 115, 115, 115, 115, 115, 115, 115, 115, 115, 115, 115, 115, 115, 115, 115, 115, 115, 116, 116, 116, 116, 116, 116, 116, 116, 116, 116, 116, 116, 116, 116, 116, 116, 116, 116, 117, 117, 117, 117, 117, 117, 117, 117, 118, 118, 118, 118, 118, 118, 118, 119, 119, 119, 119, 119, 119, 120, 120, 120, 120, 120, 120, 120, 120, 121, 121, 121, 121, 121, 121, 121, 122, 122, 122, 122, 122, 122, 123, 123, 123, 123, 123, 124, 124, 124, 124, 125, 125, 125, 126, 126, 126, 126, 126, 127, 127, 127, 127, 128, 128, 128, 129, 129, 129, 129, 129, 129, 129, 129, 129, 129, 129, 129, 129, 129, 129, 129, 129, 129, 129, 129, 129, 129, 129, 129, 129, 129, 129, 129, 129, 129, 129, 129, 129, 129, 129, 130, 130, 130, 130, 130, 130, 130, 130, 130, 130, 130, 130, 130, 130, 130, 130, 130, 130, 130, 130, 130, 130, 130, 130, 130, 130, 130, 130, 130, 130, 130, 130, 130, 130, 131, 131, 131, 131, 131, 131, 131, 131, 131, 131, 131, 131, 131, 131, 131, 131, 131, 131, 131, 131, 131, 131, 131, 131, 131, 131, 131, 131, 131, 131, 131, 131, 131, 132, 132, 132, 132, 132, 133, 133, 133, 133, 134, 134, 134, 135, 135, 135, 135, 135, 136, 136, 136, 136, 137, 137, 137, 138, 138, 138, 138, 138, 139, 139, 139, 139, 140, 140, 140, 141, 141, 141, 141, 141, 141, 141, 141, 141, 141, 141, 141, 141, 141, 141, 141, 141, 141, 141, 141, 141, 141, 141, 141, 141, 141, 141, 141, 141, 141, 141, 141, 141, 141, 141, 141, 141, 141, 142, 142, 142, 142, 142, 142, 142, 142, 142, 142, 142, 142, 142, 142, 142, 142, 142, 142, 142, 142, 142, 142, 142, 142, 142, 142, 142, 142, 142, 142, 142, 142, 142, 142, 142, 142, 142, 143, 143, 143, 143, 143, 143, 143, 143, 143, 143, 143, 143, 143, 143, 143, 143, 143, 143, 143, 143, 143, 143, 143, 143, 143, 143, 143, 143, 143, 143, 143, 143, 143, 143, 143, 143, 144, 144, 144, 144, 144, 144, 144, 144, 145, 145, 145, 145, 145, 145, 145, 146, 146, 146, 146, 146, 146, 147, 147, 147, 147, 147, 147, 147, 147, 148, 148, 148, 148, 148, 148, 148, 149, 149, 149, 149, 149, 149, 150, 150, 150, 150, 150, 151, 151, 151, 151, 152, 152, 152, 153, 153, 153, 153, 153, 153, 153, 153, 153, 153, 153, 154, 154, 154, 154, 154, 154, 154, 154, 154, 154, 155, 155, 155, 155, 155, 155, 155, 155, 155, 156, 156, 156, 156, 156, 156, 156, 156, 157, 157, 157, 157, 157, 157, 157, 158, 158, 158, 158, 158, 158, 159, 159, 159, 159, 159, 159, 159, 159, 159, 159, 159, 159, 159, 159, 159, 159, 159, 160, 160, 160, 160, 160, 160, 160, 160, 160, 160, 160, 160, 160, 160, 160, 160, 161, 161, 161, 161, 161, 161, 161, 161, 161, 161, 161, 161, 161, 161, 161, 162, 162, 162, 162, 162, 162, 162, 162, 163, 163, 163, 163, 163, 163, 163, 164, 164, 164, 164, 164, 164, 165, 165, 165, 165, 165, 165, 165, 165, 165, 165, 165, 165, 165, 165, 166, 166, 166, 166, 166, 166, 166, 166, 166, 166, 166, 166, 166, 167, 167, 167, 167, 167, 167, 167, 167, 167, 167, 167, 167, 168, 168, 168, 168, 168, 168, 168, 168, 169, 169, 169, 169, 169, 169, 169, 170, 170, 170, 170, 170, 170, 171, 171, 171, 171, 171, 171, 171, 171, 171, 171, 171, 171, 171, 171, 171, 171, 171, 171, 171, 171, 171, 171, 171, 171, 171, 171, 171, 171, 171, 172, 172, 172, 172, 172, 172, 172, 172, 172, 172, 172, 172, 172, 172, 172, 172, 172, 172, 172, 172, 172, 172, 172, 172, 172, 172, 172, 172, 173, 173, 173, 173, 173, 173, 173, 173, 173, 173, 173, 173, 173, 173, 173, 173, 173, 173, 173, 173, 173, 173, 173, 173, 173, 173, 173, 174, 174, 174, 174, 174, 174, 174, 174, 175, 175, 175, 175, 175, 175, 175, 176, 176, 176, 176, 176, 176, 177, 177, 177, 177, 177, 177, 177, 177, 178, 178, 178, 178, 178, 178, 178, 179, 179, 179, 179, 179, 179, 180, 180, 180, 180, 180, 181, 181, 181, 181, 182, 182, 182, 183, 183, 183, 183, 183, 183, 183, 183, 184, 184, 184, 184, 184, 184, 184, 185, 185, 185, 185, 185, 185, 186, 186, 186, 186, 186, 186, 186, 186, 187, 187, 187, 187, 187, 187, 187, 188, 188, 188, 188, 188, 188, 189, 189, 189, 189, 189, 189, 189, 189, 189, 189, 189, 190, 190, 190, 190, 190, 190, 190, 190, 190, 190, 191, 191, 191, 191, 191, 191, 191, 191, 191, 192, 192, 192, 192, 192, 192, 192, 192, 193, 193, 193, 193, 193, 193, 193, 194, 194, 194, 194, 194, 194, 195, 195, 195, 195, 195, 195, 195, 195, 195, 195, 195, 195, 195, 195, 195, 195, 195, 196, 196, 196, 196, 196, 196, 196, 196, 196, 196, 196, 196, 196, 196, 196, 196, 197, 197, 197, 197, 197, 197, 197, 197, 197, 197, 197, 197, 197, 197, 197, 198, 198, 198, 198, 198, 198, 198, 198, 199, 199, 199, 199, 199, 199, 199, 200, 200, 200, 200, 200, 200, 201, 201, 201, 201, 201, 201, 201, 201, 202, 202, 202, 202, 202, 202, 202, 203, 203, 203, 203, 203, 203, 204, 204, 204, 204, 204, 204, 204, 204, 205, 205, 205, 205, 205, 205, 205, 206, 206, 206, 206, 206, 206, 207, 207, 207, 207, 207, 207, 207, 207, 207, 207, 207, 207, 207, 207, 207, 207, 207, 207, 207, 207, 208, 208, 208, 208, 208, 208, 208, 208, 208, 208, 208, 208, 208, 208, 208, 208, 208, 208, 208, 209, 209, 209, 209, 209, 209, 209, 209, 209, 209, 209, 209, 209, 209, 209, 209, 209, 209, 210, 210, 210, 210, 210, 210, 210, 210, 210, 210, 210, 210, 210, 210, 210, 210, 210, 211, 211, 211, 211, 211, 211, 211, 211, 211, 211, 211, 211, 211, 211, 211, 211, 212, 212, 212, 212, 212, 212, 212, 212, 212, 212, 212, 212, 212, 212, 212, 213, 213, 213, 213, 213, 214, 214, 214, 214, 215, 215, 215, 216, 216, 217, 219, 219, 220, 222, 222, 223, 225, 225, 226, 228, 228, 229, 231, 231, 232, 234, 234, 235, 237, 237, 238, 240, 240, 240, 240, 240, 240, 240, 240, 241, 241, 241, 241, 241, 241, 241, 242, 242, 242, 242, 242, 242, 243, 243, 244, 246, 246, 246, 246, 246, 247, 247, 247, 247, 248, 248, 248, 249, 249, 250, 252, 252, 253, 255, 255, 255, 255, 255, 255, 255, 255, 255, 255, 255, 255, 255, 255, 255, 255, 255, 256, 256, 256, 256, 256, 256, 256, 256, 256, 256, 256, 256, 256, 256, 256, 256, 257, 257, 257, 257, 257, 257, 257, 257, 257, 257, 257, 257, 257, 257, 257, 258, 258, 258, 258, 258, 259, 259, 259, 259, 260, 260, 260, 261, 261, 261, 261, 261, 261, 261, 261, 262, 262, 262, 262, 262, 262, 262, 263, 263, 263, 263, 263, 263, 264, 264, 265, 267, 267, 267, 267, 267, 267, 267, 267, 267, 267, 267, 267, 267, 267, 268, 268, 268, 268, 268, 268, 268, 268, 268, 268, 268, 268, 268, 269, 269, 269, 269, 269, 269, 269, 269, 269, 269, 269, 269, 270, 270, 270, 270, 270, 271, 271, 271, 271, 272, 272, 272, 273, 273, 274, 276, 276, 276, 276, 276, 277, 277, 277, 277, 278, 278, 278, 279, 279, 279, 279, 279, 280, 280, 280, 280, 281, 281, 281, 282, 282, 282, 282, 282, 283, 283, 283, 283, 284, 284, 284, 285, 285, 285, 285, 285, 286, 286, 286, 286, 287, 287, 287, 288, 288, 288, 288, 288, 289, 289, 289, 289, 290, 290, 290, 291, 291, 291, 291, 291, 292, 292, 292, 292, 293, 293, 293, 294, 294, 294, 294, 294, 294, 294, 294, 294, 294, 294, 295, 295, 295, 295, 295, 295, 295, 295, 295, 295, 296, 296, 296, 296, 296, 296, 296, 296, 296, 297, 297, 297, 297, 297, 297, 297, 297, 298, 298, 298, 298, 298, 298, 298, 299, 299, 299, 299, 299, 299, 300, 300, 300, 300, 300, 301, 301, 301, 301, 302, 302, 302, 303, 303, 303, 303, 303, 304, 304, 304, 304, 305, 305, 305, 306, 306, 306, 306, 306, 306, 306, 306, 306, 306, 306, 307, 307, 307, 307, 307, 307, 307, 307, 307, 307, 308, 308, 308, 308, 308, 308, 308, 308, 308, 309, 309, 309, 309, 309, 310, 310, 310, 310, 311, 311, 311, 312, 312, 312, 312, 312, 313, 313, 313, 313, 314, 314, 314, 315, 315, 315, 315, 315, 316, 316, 316, 316, 317, 317, 317, 318, 318, 318, 318, 318, 319, 319, 319, 319, 320, 320, 320, 321, 321, 321, 321, 321, 322, 322, 322, 322, 323, 323, 323, 324, 324, 324, 324, 324, 325, 325, 325, 325, 326, 326, 326, 327, 327, 327, 327, 327, 328, 328, 328, 328, 329, 329, 329, 330, 330, 330, 330, 330, 331, 331, 331, 331, 332, 332, 332, 333, 333, 333, 333, 333, 334, 334, 334, 334, 335, 335, 335, 336, 336, 337, 339, 339, 340, 342, 342, 343, 345, 345, 346, 348, 348, 349, 351, 351, 352, 354, 354, 355, 357, 357, 358, 360, 360, 361, 363, 363, 364, 366, 366, 367, 369, 369, 370, 372, 372, 373, 375, 375, 376, 378, 378, 379, 381, 381, 382, 384, 384, 385, 387, 387, 388, 390, 390, 391, 393, 393, 394, 396, 396, 397, 399, 399, 400, 402, 402, 403, 405, 405, 406, 408, 408, 409, 411, 411, 412, 414, 414, 415, 417, 417, 418, 420, 420, 421, 423, 423, 424, 426, 426, 427, 429, 429, 430, 432, 432, 433, 435, 435, 436, 438, 438, 439, 441, 441, 442, 444, 444, 445, 447, 447, 448, 450, 450, 451], "quadratic_tail": [1, 2, 198, 199, 200, 201, 202, 203, 327, 328, 329, 438, 439, 440, 2, 198, 199, 200, 201, 202, 203, 327, 328, 329, 438, 439, 440, 198, 199, 200, 201, 202, 203, 327, 328, 329, 438, 439, 440, 4, 5, 201, 202, 203, 438, 439, 440, 5, 201, 202, 203, 438, 439, 440, 201, 202, 203, 438, 439, 440, 7, 8, 201, 202, 203, 438, 439, 440, 8, 201, 202, 203, 438, 439, 440, 201, 202, 203, 438, 439, 440, 10, 11, 201, 202, 203, 330, 331, 332, 438, 439, 440, 11, 201, 202, 203, 330, 331, 332, 438, 439, 440, 201, 202, 203, 330, 331, 332, 438, 439, 440, 13, 14, 204, 205, 206, 330, 331, 332, 438, 439, 440, 14, 204, 205, 206, 330, 331, 332, 438, 439, 440, 204, 205, 206, 330, 331, 332, 438, 439, 440, 16, 17, 207, 208, 209, 210, 211, 212, 438, 439, 440, 441, 442, 443, 444, 445, 446, 447, 448, 449, 450, 451, 452, 17, 207, 208, 209, 210, 211, 212, 438, 439, 440, 441, 442, 443, 444, 445, 446, 447, 448, 449, 450, 451, 452, 207, 208, 209, 210, 211, 212, 438, 439, 440, 441, 442, 443, 444, 445, 446, 447, 448, 449, 450, 451, 452, 19, 20, 117, 118, 119, 210, 211, 212, 450, 451, 452, 20, 117, 118, 119, 210, 211, 212, 450, 451, 452, 117, 118, 119, 210, 211, 212, 450, 451, 452, 22, 23, 120, 121, 122, 213, 214, 215, 336, 337, 338, 23, 120, 121, 122, 213, 214, 215, 336, 337, 338, 120, 121, 122, 213, 214, 215, 336, 337, 338, 25, 26, 123, 124, 125, 216, 217, 218, 26, 123, 124, 125, 216, 217, 218, 123, 124, 125, 216, 217, 218, 28, 29, 126, 127, 128, 219, 220, 221, 29, 126, 127, 128, 219, 220, 221, 126, 127, 128, 219, 220, 221, 31, 32, 147, 148, 149, 240, 241, 242, 366, 367, 368, 32, 147, 148, 149, 240, 241, 242, 366, 367, 368, 147, 148, 149, 240, 241, 242, 366, 367, 368, 34, 35, 129, 130, 131, 222, 223, 224, 225, 226, 227, 228, 229, 230, 231, 232, 233, 234, 235, 236, 237, 238, 239, 351, 352, 353, 354, 355, 356, 357, 358, 359, 360, 361, 362, 363, 364, 365, 35, 129, 130, 131, 222, 223, 224, 225, 226, 227, 228, 229, 230, 231, 232, 233, 234, 235, 236, 237, 238, 239, 351, 352, 353, 354, 355, 356, 357, 358, 359, 360, 361, 362, 363, 364, 365, 129, 130, 131, 222, 223, 224, 225, 226, 227, 228, 229, 230, 231, 232, 233, 234, 235, 236, 237, 238, 239, 351, 352, 353, 354, 355, 356, 357, 358, 359, 360, 361, 362, 363, 364, 365, 37, 38, 132, 133, 134, 135, 136, 137, 243, 244, 245, 363, 364, 365, 369, 370, 371, 38, 132, 133, 134, 135, 136, 137, 243, 244, 245, 363, 364, 365, 369, 370, 371, 132, 133, 134, 135, 136, 137, 243, 244, 245, 363, 364, 365, 369, 370, 371, 40, 41, 138, 139, 140, 243, 244, 245, 41, 138, 139, 140, 243, 244, 245, 138, 139, 140, 243, 244, 245, 43, 44, 141, 142, 143, 249, 250, 251, 252, 253, 254, 255, 256, 257, 378, 379, 380, 381, 382, 383, 384, 385, 386, 44, 141, 142, 143, 249, 250, 251, 252, 253, 254, 255, 256, 257, 378, 379, 380, 381, 382, 383, 384, 385, 386, 141, 142, 143, 249, 250, 251, 252, 253, 254, 255, 256, 257, 378, 379, 380, 381, 382, 383, 384, 385, 386, 46, 47, 141, 142, 143, 255, 256, 257, 384, 385, 386, 47, 141, 142, 143, 255, 256, 257, 384, 385, 386, 141, 142, 143, 255, 256, 257, 384, 385, 386, 49, 50, 141, 142, 143, 255, 256, 257, 384, 385, 386, 387, 388, 389, 390, 391, 392, 50, 141, 142, 143, 255, 256, 257, 384, 385, 386, 387, 388, 389, 390, 391, 392, 141, 142, 143, 255, 256, 257, 384, 385, 386, 387, 388, 389, 390, 391, 392, 52, 53, 141, 142, 143, 258, 259, 260, 261, 262, 263, 393, 394, 395, 396, 397, 398, 53, 141, 142, 143, 258, 259, 260, 261, 262, 263, 393, 394, 395, 396, 397, 398, 141, 142, 143, 258, 259, 260, 261, 262, 263, 393, 394, 395, 396, 397, 398, 55, 56, 144, 145, 146, 261, 262, 263, 396, 397, 398, 56, 144, 145, 146, 261, 262, 263, 396, 397, 398, 144, 145, 146, 261, 262, 263, 396, 397, 398, 58, 59, 150, 151, 152, 153, 154, 155, 261, 262, 263, 264, 265, 266, 267, 268, 269, 405, 406, 407, 59, 150, 151, 152, 153, 154, 155, 261, 262, 263, 264, 265, 266, 267, 268, 269, 405, 406, 407, 150, 151, 152, 153, 154, 155, 261, 262, 263, 264, 265, 266, 267, 268, 269, 405, 406, 407, 61, 62, 156, 157, 158, 267, 268, 269, 408, 409, 410, 62, 156, 157, 158, 267, 268, 269, 408, 409, 410, 156, 157, 158, 267, 268, 269, 408, 409, 410, 64, 65, 147, 148, 149, 240, 241, 242, 366, 367, 368, 65, 147, 148, 149, 240, 241, 242, 366, 367, 368, 147, 148, 149, 240, 241, 242, 366, 367, 368, 67, 68, 159, 160, 161, 267, 268, 269, 68, 159, 160, 161, 267, 268, 269, 159, 160, 161, 267, 268, 269, 70, 71, 159, 160, 161, 270, 271, 272, 417, 418, 419, 71, 159, 160, 161, 270, 271, 272, 417, 418, 419, 159, 160, 161, 270, 271, 272, 417, 418, 419, 73, 74, 159, 160, 161, 276, 277, 278, 417, 418, 419, 74, 159, 160, 161, 276, 277, 278, 417, 418, 419, 159, 160, 161, 276, 277, 278, 417, 418, 419, 76, 77, 159, 160, 161, 279, 280, 281, 417, 418, 419, 77, 159, 160, 161, 279, 280, 281, 417, 418, 419, 159, 160, 161, 279, 280, 281, 417, 418, 419, 79, 80, 162, 163, 164, 282, 283, 284, 417, 418, 419, 80, 162, 163, 164, 282, 283, 284, 417, 418, 419, 162, 163, 164, 282, 283, 284, 417, 418, 419, 82, 83, 165, 166, 167, 282, 283, 284, 285, 286, 287, 417, 418, 419, 83, 165, 166, 167, 282, 283, 284, 285, 286, 287, 417, 418, 419, 165, 166, 167, 282, 283, 284, 285, 286, 287, 417, 418, 419, 85, 86, 165, 166, 167, 288, 289, 290, 417, 418, 419, 86, 165, 166, 167, 288, 289, 290, 417, 418, 419, 165, 166, 167, 288, 289, 290, 417, 418, 419, 88, 89, 168, 169, 170, 288, 289, 290, 417, 418, 419, 89, 168, 169, 170, 288, 289, 290, 417, 418, 419, 168, 169, 170, 288, 289, 290, 417, 418, 419, 91, 92, 171, 172, 173, 174, 175, 176, 294, 295, 296, 297, 298, 299, 300, 301, 302, 303, 304, 305, 309, 310, 311, 417, 418, 419, 420, 421, 422, 423, 424, 425, 426, 427, 428, 429, 430, 431, 92, 171, 172, 173, 174, 175, 176, 294, 295, 296, 297, 298, 299, 300, 301, 302, 303, 304, 305, 309, 310, 311, 417, 418, 419, 420, 421, 422, 423, 424, 425, 426, 427, 428, 429, 430, 431, 171, 172, 173, 174, 175, 176, 294, 295, 296, 297, 298, 299, 300, 301, 302, 303, 304, 305, 309, 310, 311, 417, 418, 419, 420, 421, 422, 423, 424, 425, 426, 427, 428, 429, 430, 431, 94, 95, 177, 178, 179, 183, 184, 185, 186, 187, 188, 309, 310, 311, 312, 313, 314, 315, 316, 317, 429, 430, 431, 95, 177, 178, 179, 183, 184, 185, 186, 187, 188, 309, 310, 311, 312, 313, 314, 315, 316, 317, 429, 430, 431, 177, 178, 179, 183, 184, 185, 186, 187, 188, 309, 310, 311, 312, 313, 314, 315, 316, 317, 429, 430, 431, 97, 98, 180, 181, 182, 189, 190, 191, 240, 241, 242, 273, 274, 275, 306, 307, 308, 432, 433, 434, 98, 180, 181, 182, 189, 190, 191, 240, 241, 242, 273, 274, 275, 306, 307, 308, 432, 433, 434, 180, 181, 182, 189, 190, 191, 240, 241, 242, 273, 274, 275, 306, 307, 308, 432, 433, 434, 100, 101, 192, 193, 194, 306, 307, 308, 432, 433, 434, 101, 192, 193, 194, 306, 307, 308, 432, 433, 434, 192, 193, 194, 306, 307, 308, 432, 433, 434, 103, 104, 195, 196, 197, 306, 307, 308, 104, 195, 196, 197, 306, 307, 308, 195, 196, 197, 306, 307, 308, 106, 107, 195, 196, 197, 306, 307, 308, 107, 195, 196, 197, 306, 307, 308, 195, 196, 197, 306, 307, 308, 109, 110, 195, 196, 197, 306, 307, 308, 438, 439, 440, 110, 195, 196, 197, 306, 307, 308, 438, 439, 440, 195, 196, 197, 306, 307, 308, 438, 439, 440, 112, 113, 195, 196, 197, 306, 307, 308, 438, 439, 440, 113, 195, 196, 197, 306, 307, 308, 438, 439, 440, 195, 196, 197, 306, 307, 308, 438, 439, 440, 115, 116, 195, 196, 197, 306, 307, 308, 318, 319, 320, 321, 322, 323, 324, 325, 326, 438, 439, 440, 116, 195, 196, 197, 306, 307, 308, 318, 319, 320, 321, 322, 323, 324, 325, 326, 438, 439, 440, 195, 196, 197, 306, 307, 308, 318, 319, 320, 321, 322, 323, 324, 325, 326, 438, 439, 440, 118, 119, 210, 211, 212, 450, 451, 452, 119, 210, 211, 212, 450, 451, 452, 210, 211, 212, 450, 451, 452, 121, 122, 213, 214, 215, 336, 337, 338, 122, 213, 214, 215, 336, 337, 338, 213, 214, 215, 336, 337, 338, 124, 125, 216, 217, 218, 125, 216, 217, 218, 216, 217, 218, 127, 128, 219, 220, 221, 128, 219, 220, 221, 219, 220, 221, 130, 131, 222, 223, 224, 225, 226, 227, 228, 229, 230, 231, 232, 233, 234, 235, 236, 237, 238, 239, 351, 352, 353, 354, 355, 356, 357, 358, 359, 360, 361, 362, 363, 364, 365, 131, 222, 223, 224, 225, 226, 227, 228, 229, 230, 231, 232, 233, 234, 235, 236, 237, 238, 239, 351, 352, 353, 354, 355, 356, 357, 358, 359, 360, 361, 362, 363, 364, 365, 222, 223, 224, 225, 226, 227, 228, 229, 230, 231, 232, 233, 234, 235, 236, 237, 238, 239, 351, 352, 353, 354, 355, 356, 357, 358, 359, 360, 361, 362, 363, 364, 365, 133, 134, 363, 364, 365, 134, 363, 364, 365, 363, 364, 365, 136, 137, 243, 244, 245, 137, 243, 244, 245, 243, 244, 245, 139, 140, 243, 244, 245, 140, 243, 244, 245, 243, 244, 245, 142, 143, 249, 250, 251, 252, 253, 254, 255, 256, 257, 258, 259, 260, 261, 262, 263, 378, 379, 380, 381, 382, 383, 384, 385, 386, 387, 388, 389, 390, 391, 392, 393, 394, 395, 396, 397, 398, 143, 249, 250, 251, 252, 253, 254, 255, 256, 257, 258, 259, 260, 261, 262, 263, 378, 379, 380, 381, 382, 383, 384, 385, 386, 387, 388, 389, 390, 391, 392, 393, 394, 395, 396, 397, 398, 249, 250, 251, 252, 253, 254, 255, 256, 257, 258, 259, 260, 261, 262, 263, 378, 379, 380, 381, 382, 383, 384, 385, 386, 387, 388, 389, 390, 391, 392, 393, 394, 395, 396, 397, 398, 145, 146, 261, 262, 263, 396, 397, 398, 146, 261, 262, 263, 396, 397, 398, 261, 262, 263, 396, 397, 398, 148, 149, 240, 241, 242, 366, 367, 368, 149, 240, 241, 242, 366, 367, 368, 240, 241, 242, 366, 367, 368, 151, 152, 261, 262, 263, 152, 261, 262, 263, 261, 262, 263, 154, 155, 264, 265, 266, 267, 268, 269, 405, 406, 407, 155, 264, 265, 266, 267, 268, 269, 405, 406, 407, 264, 265, 266, 267, 268, 269, 405, 406, 407, 157, 158, 267, 268, 269, 408, 409, 410, 158, 267, 268, 269, 408, 409, 410, 267, 268, 269, 408, 409, 410, 160, 161, 267, 268, 269, 270, 271, 272, 276, 277, 278, 279, 280, 281, 417, 418, 419, 161, 267, 268, 269, 270, 271, 272, 276, 277, 278, 279, 280, 281, 417, 418, 419, 267, 268, 269, 270, 271, 272, 276, 277, 278, 279, 280, 281, 417, 418, 419, 163, 164, 282, 283, 284, 417, 418, 419, 164, 282, 283, 284, 417, 418, 419, 282, 283, 284, 417, 418, 419, 166, 167, 282, 283, 284, 285, 286, 287, 288, 289, 290, 417, 418, 419, 167, 282, 283, 284, 285, 286, 287, 288, 289, 290, 417, 418, 419, 282, 283, 284, 285, 286, 287, 288, 289, 290, 417, 418, 419, 169, 170, 288, 289, 290, 417, 418, 419, 170, 288, 289, 290, 417, 418, 419, 288, 289, 290, 417, 418, 419, 172, 173, 294, 295, 296, 297, 298, 299, 300, 301, 302, 303, 304, 305, 417, 418, 419, 420, 421, 422, 423, 424, 425, 426, 427, 428, 429, 430, 431, 173, 294, 295, 296, 297, 298, 299, 300, 301, 302, 303, 304, 305, 417, 418, 419, 420, 421, 422, 423, 424, 425, 426, 427, 428, 429, 430, 431, 294, 295, 296, 297, 298, 299, 300, 301, 302, 303, 304, 305, 417, 418, 419, 420, 421, 422, 423, 424, 425, 426, 427, 428, 429, 430, 431, 175, 176, 309, 310, 311, 429, 430, 431, 176, 309, 310, 311, 429, 430, 431, 309, 310, 311, 429, 430, 431, 178, 179, 309, 310, 311, 429, 430, 431, 179, 309, 310, 311, 429, 430, 431, 309, 310, 311, 429, 430, 431, 181, 182, 240, 241, 242, 182, 240, 241, 242, 240, 241, 242, 184, 185, 312, 313, 314, 429, 430, 431, 185, 312, 313, 314, 429, 430, 431, 312, 313, 314, 429, 430, 431, 187, 188, 315, 316, 317, 429, 430, 431, 188, 315, 316, 317, 429, 430, 431, 315, 316, 317, 429, 430, 431, 190, 191, 273, 274, 275, 306, 307, 308, 432, 433, 434, 191, 273, 274, 275, 306, 307, 308, 432, 433, 434, 273, 274, 275, 306, 307, 308, 432, 433, 434, 193, 194, 306, 307, 308, 432, 433, 434, 194, 306, 307, 308, 432, 433, 434, 306, 307, 308, 432, 433, 434, 196, 197, 306, 307, 308, 318, 319, 320, 321, 322, 323, 324, 325, 326, 438, 439, 440, 197, 306, 307, 308, 318, 319, 320, 321, 322, 323, 324, 325, 326, 438, 439, 440, 306, 307, 308, 318, 319, 320, 321, 322, 323, 324, 325, 326, 438, 439, 440, 199, 200, 327, 328, 329, 438, 439, 440, 200, 327, 328, 329, 438, 439, 440, 327, 328, 329, 438, 439, 440, 202, 203, 330, 331, 332, 438, 439, 440, 203, 330, 331, 332, 438, 439, 440, 330, 331, 332, 438, 439, 440, 205, 206, 330, 331, 332, 438, 439, 440, 206, 330, 331, 332, 438, 439, 440, 330, 331, 332, 438, 439, 440, 208, 209, 210, 211, 212, 438, 439, 440, 441, 442, 443, 444, 445, 446, 447, 448, 449, 450, 451, 452, 209, 210, 211, 212, 438, 439, 440, 441, 442, 443, 444, 445, 446, 447, 448, 449, 450, 451, 452, 210, 211, 212, 438, 439, 440, 441, 442, 443, 444, 445, 446, 447, 448, 449, 450, 451, 452, 211, 212, 438, 439, 440, 441, 442, 443, 444, 445, 446, 447, 448, 449, 450, 451, 452, 212, 438, 439, 440, 441, 442, 443, 444, 445, 446, 447, 448, 449, 450, 451, 452, 438, 439, 440, 441, 442, 443, 444, 445, 446, 447, 448, 449, 450, 451, 452, 214, 215, 336, 337, 338, 215, 336, 337, 338, 336, 337, 338, 217, 218, 218, 220, 221, 221, 223, 224, 224, 226, 227, 227, 229, 230, 230, 232, 233, 233, 235, 236, 236, 238, 239, 239, 241, 242, 366, 367, 368, 399, 400, 401, 242, 366, 367, 368, 399, 400, 401, 366, 367, 368, 399, 400, 401, 244, 245, 245, 247, 248, 372, 373, 374, 248, 372, 373, 374, 372, 373, 374, 250, 251, 251, 253, 254, 254, 256, 257, 378, 379, 380, 381, 382, 383, 384, 385, 386, 387, 388, 389, 390, 391, 392, 257, 378, 379, 380, 381, 382, 383, 384, 385, 386, 387, 388, 389, 390, 391, 392, 378, 379, 380, 381, 382, 383, 384, 385, 386, 387, 388, 389, 390, 391, 392, 259, 260, 393, 394, 395, 260, 393, 394, 395, 393, 394, 395, 262, 263, 396, 397, 398, 402, 403, 404, 263, 396, 397, 398, 402, 403, 404, 396, 397, 398, 402, 403, 404, 265, 266, 266, 268, 269, 405, 406, 407, 408, 409, 410, 411, 412, 413, 414, 415, 416, 269, 405, 406, 407, 408, 409, 410, 411, 412, 413, 414, 415, 416, 405, 406, 407, 408, 409, 410, 411, 412, 413, 414, 415, 416, 271, 272, 417, 418, 419, 272, 417, 418, 419, 417, 418, 419, 274, 275, 275, 277, 278, 417, 418, 419, 278, 417, 418, 419, 417, 418, 419, 280, 281, 417, 418, 419, 281, 417, 418, 419, 417, 418, 419, 283, 284, 417, 418, 419, 284, 417, 418, 419, 417, 418, 419, 286, 287, 417, 418, 419, 287, 417, 418, 419, 417, 418, 419, 289, 290, 417, 418, 419, 290, 417, 418, 419, 417, 418, 419, 292, 293, 417, 418, 419, 293, 417, 418, 419, 417, 418, 419, 295, 296, 417, 418, 419, 420, 421, 422, 423, 424, 425, 296, 417, 418, 419, 420, 421, 422, 423, 424, 425, 417, 418, 419, 420, 421, 422, 423, 424, 425, 298, 299, 426, 427, 428, 429, 430, 431, 299, 426, 427, 428, 429, 430, 431, 426, 427, 428, 429, 430, 431, 301, 302, 429, 430, 431, 302, 429, 430, 431, 429, 430, 431, 304, 305, 429, 430, 431, 305, 429, 430, 431, 429, 430, 431, 307, 308, 432, 433, 434, 435, 436, 437, 438, 439, 440, 308, 432, 433, 434, 435, 436, 437, 438, 439, 440, 432, 433, 434, 435, 436, 437, 438, 439, 440, 310, 311, 429, 430, 431, 311, 429, 430, 431, 429, 430, 431, 313, 314, 429, 430, 431, 314, 429, 430, 431, 429, 430, 431, 316, 317, 429, 430, 431, 317, 429, 430, 431, 429, 430, 431, 319, 320, 438, 439, 440, 320, 438, 439, 440, 438, 439, 440, 322, 323, 438, 439, 440, 323, 438, 439, 440, 438, 439, 440, 325, 326, 438, 439, 440, 326, 438, 439, 440, 438, 439, 440, 328, 329, 438, 439, 440, 329, 438, 439, 440, 438, 439, 440, 331, 332, 438, 439, 440, 332, 438, 439, 440, 438, 439, 440, 334, 335, 438, 439, 440, 335, 438, 439, 440, 438, 439, 440, 337, 338, 338, 340, 341, 341, 343, 344, 344, 346, 347, 347, 349, 350, 350, 352, 353, 353, 355, 356, 356, 358, 359, 359, 361, 362, 362, 364, 365, 365, 367, 368, 368, 370, 371, 371, 373, 374, 374, 376, 377, 377, 379, 380, 380, 382, 383, 383, 385, 386, 386, 388, 389, 389, 391, 392, 392, 394, 395, 395, 397, 398, 398, 400, 401, 401, 403, 404, 404, 406, 407, 407, 409, 410, 410, 412, 413, 413, 415, 416, 416, 418, 419, 419, 421, 422, 422, 424, 425, 425, 427, 428, 428, 430, 431, 431, 433, 434, 434, 436, 437, 437, 439, 440, 440, 442, 443, 443, 445, 446, 446, 448, 449, 449, 451, 452, 452]}